<metadata xml:lang="en"><Esri><CreaDate>20140102</CreaDate><CreaTime>19185400</CreaTime><ArcGISFormat>1.0</ArcGISFormat><SyncOnce>FALSE</SyncOnce><DataProperties><lineage><Process ToolSource="E:\Program Files (x86)\ArcGIS\Desktop10.0\ArcToolbox\Toolboxes\Data Management Tools.tbx\CreateFeatureclass" Date="20140102" Time="191854">CreateFeatureclass E:\code\Spatial\Connections\OPS$GEODATA_D2CS01.sde GEO2013_TRACT_P2G3_A POLYGON G:\load\en\GEO\2013\spatial\geo_2013_g_01000_140_00_py_z6-20131230163449.shp SAME_AS_TEMPLATE SAME_AS_TEMPLATE "PROJCS['WGS_1984_Web_Mercator_Auxiliary_Sphere',GEOGCS['GCS_WGS_1984',DATUM['D_WGS_1984',SPHEROID['WGS_1984',6378137.0,298.257223563]],PRIMEM['Greenwich',0.0],UNIT['Degree',0.0174532925199433]],PROJECTION['Mercator_Auxiliary_Sphere'],PARAMETER['False_Easting',0.0],PARAMETER['False_Northing',0.0],PARAMETER['Central_Meridian',0.0],PARAMETER['Standard_Parallel_1',0.0],PARAMETER['Auxiliary_Sphere_Type',0.0],UNIT['Meter',1.0]];-20037700 -30241100 10000;-100000 10000;-100000 10000;0.001;0.001;0.001;IsHighPrecision" ST_GEOMETRY 0 0 0</Process><Process ToolSource="E:\Program Files (x86)\ArcGIS\Desktop10.0\ArcToolbox\Toolboxes\Data Management Tools.tbx\ChangePrivileges" Date="20140102" Time="191854">ChangePrivileges E:\code\Spatial\Connections\OPS$GEODATA_D2CS01.sde\GEO2013_TRACT_P2G3_A SPATIAL_META2010_RW GRANT AS_IS</Process><Process ToolSource="E:\Program Files (x86)\ArcGIS\Desktop10.0\ArcToolbox\Toolboxes\Data Management Tools.tbx\RemoveSpatialIndex" Date="20140102" Time="191855">RemoveSpatialIndex E:\code\Spatial\Connections\OPS$GEODATA_D2CS01.sde\GEO2013_TRACT_P2G3_A</Process><Process ToolSource="E:\Program Files (x86)\ArcGIS\Desktop10.0\ArcToolbox\Toolboxes\Data Management Tools.tbx\Append" Date="20140102" Time="191908">Append G:\load\en\GEO\2013\spatial\geo_2013_g_01000_140_00_py_z6-20131230163449.shp E:\code\Spatial\Connections\OPS$GEODATA_D2CS01.sde\GEO2013_TRACT_P2G3_A TEST # #</Process><Process ToolSource="E:\Program Files (x86)\ArcGIS\Desktop10.0\ArcToolbox\Toolboxes\Data Management Tools.tbx\Append" Date="20140102" Time="192605">Append G:\load\en\GEO\2013\spatial\geo_2013_g_05000_140_00_py_z6-20131230163449.shp E:\code\Spatial\Connections\OPS$GEODATA_D2CS01.sde\GEO2013_TRACT_P2G3_A TEST # #</Process><Process ToolSource="E:\Program Files (x86)\ArcGIS\Desktop10.0\ArcToolbox\Toolboxes\Data Management Tools.tbx\Append" Date="20140102" Time="193317">Append G:\load\en\GEO\2013\spatial\geo_2013_g_21000_140_00_py_z6-20131230163449.shp E:\code\Spatial\Connections\OPS$GEODATA_D2CS01.sde\GEO2013_TRACT_P2G3_A TEST # #</Process><Process ToolSource="E:\Program Files (x86)\ArcGIS\Desktop10.0\ArcToolbox\Toolboxes\Data Management Tools.tbx\Append" Date="20140102" Time="193558">Append G:\load\en\GEO\2013\spatial\geo_2013_g_22000_140_00_py_z6-20131230163449.shp E:\code\Spatial\Connections\OPS$GEODATA_D2CS01.sde\GEO2013_TRACT_P2G3_A TEST # #</Process><Process ToolSource="E:\Program Files (x86)\ArcGIS\Desktop10.0\ArcToolbox\Toolboxes\Data Management Tools.tbx\Append" Date="20140102" Time="194046">Append G:\load\en\GEO\2013\spatial\geo_2013_g_16000_140_00_py_z6-20131230163449.shp E:\code\Spatial\Connections\OPS$GEODATA_D2CS01.sde\GEO2013_TRACT_P2G3_A TEST # #</Process><Process ToolSource="E:\Program Files (x86)\ArcGIS\Desktop10.0\ArcToolbox\Toolboxes\Data Management Tools.tbx\Append" Date="20140102" Time="194803">Append G:\load\en\GEO\2013\spatial\geo_2013_g_18000_140_00_py_z6-20131230163449.shp E:\code\Spatial\Connections\OPS$GEODATA_D2CS01.sde\GEO2013_TRACT_P2G3_A TEST # #</Process><Process ToolSource="E:\Program Files (x86)\ArcGIS\Desktop10.0\ArcToolbox\Toolboxes\Data Management Tools.tbx\Append" Date="20140102" Time="200012">Append G:\load\en\GEO\2013\spatial\geo_2013_g_02000_140_00_py_z6-20131230163449.shp E:\code\Spatial\Connections\OPS$GEODATA_D2CS01.sde\GEO2013_TRACT_P2G3_A TEST # #</Process><Process ToolSource="E:\Program Files (x86)\ArcGIS\Desktop10.0\ArcToolbox\Toolboxes\Data Management Tools.tbx\Append" Date="20140102" Time="201440">Append G:\load\en\GEO\2013\spatial\geo_2013_g_19000_140_00_py_z6-20131230163449.shp E:\code\Spatial\Connections\OPS$GEODATA_D2CS01.sde\GEO2013_TRACT_P2G3_A TEST # #</Process><Process ToolSource="E:\Program Files (x86)\ArcGIS\Desktop10.0\ArcToolbox\Toolboxes\Data Management Tools.tbx\Append" Date="20140102" Time="201604">Append G:\load\en\GEO\2013\spatial\geo_2013_g_06000_140_00_py_z6-20131230163449.shp E:\code\Spatial\Connections\OPS$GEODATA_D2CS01.sde\GEO2013_TRACT_P2G3_A TEST # #</Process><Process ToolSource="E:\Program Files (x86)\ArcGIS\Desktop10.0\ArcToolbox\Toolboxes\Data Management Tools.tbx\Append" Date="20140102" Time="202614">Append G:\load\en\GEO\2013\spatial\geo_2013_g_12000_140_00_py_z6-20131230163449.shp E:\code\Spatial\Connections\OPS$GEODATA_D2CS01.sde\GEO2013_TRACT_P2G3_A TEST # #</Process><Process ToolSource="E:\Program Files (x86)\ArcGIS\Desktop10.0\ArcToolbox\Toolboxes\Data Management Tools.tbx\Append" Date="20140102" Time="203250">Append G:\load\en\GEO\2013\spatial\geo_2013_g_15000_140_00_py_z6-20131230163449.shp E:\code\Spatial\Connections\OPS$GEODATA_D2CS01.sde\GEO2013_TRACT_P2G3_A TEST # #</Process><Process ToolSource="E:\Program Files (x86)\ArcGIS\Desktop10.0\ArcToolbox\Toolboxes\Data Management Tools.tbx\Append" Date="20140102" Time="203528">Append G:\load\en\GEO\2013\spatial\geo_2013_g_10000_140_00_py_z6-20131230163449.shp E:\code\Spatial\Connections\OPS$GEODATA_D2CS01.sde\GEO2013_TRACT_P2G3_A TEST # #</Process><Process ToolSource="E:\Program Files (x86)\ArcGIS\Desktop10.0\ArcToolbox\Toolboxes\Data Management Tools.tbx\Append" Date="20140102" Time="203953">Append G:\load\en\GEO\2013\spatial\geo_2013_g_30000_140_00_py_z6-20131230163449.shp E:\code\Spatial\Connections\OPS$GEODATA_D2CS01.sde\GEO2013_TRACT_P2G3_A TEST # #</Process><Process ToolSource="E:\Program Files (x86)\ArcGIS\Desktop10.0\ArcToolbox\Toolboxes\Data Management Tools.tbx\Append" Date="20140102" Time="204420">Append G:\load\en\GEO\2013\spatial\geo_2013_g_38000_140_00_py_z6-20131230163449.shp E:\code\Spatial\Connections\OPS$GEODATA_D2CS01.sde\GEO2013_TRACT_P2G3_A TEST # #</Process><Process ToolSource="E:\Program Files (x86)\ArcGIS\Desktop10.0\ArcToolbox\Toolboxes\Data Management Tools.tbx\Append" Date="20140102" Time="204721">Append G:\load\en\GEO\2013\spatial\geo_2013_g_69000_140_00_py_z6-20131230163449.shp E:\code\Spatial\Connections\OPS$GEODATA_D2CS01.sde\GEO2013_TRACT_P2G3_A TEST # #</Process><Process ToolSource="E:\Program Files (x86)\ArcGIS\Desktop10.0\ArcToolbox\Toolboxes\Data Management Tools.tbx\Append" Date="20140102" Time="204820">Append G:\load\en\GEO\2013\spatial\geo_2013_g_60000_140_00_py_z6-20131230163449.shp E:\code\Spatial\Connections\OPS$GEODATA_D2CS01.sde\GEO2013_TRACT_P2G3_A TEST # #</Process><Process ToolSource="E:\Program Files (x86)\ArcGIS\Desktop10.0\ArcToolbox\Toolboxes\Data Management Tools.tbx\Append" Date="20140102" Time="205146">Append G:\load\en\GEO\2013\spatial\geo_2013_g_78000_140_00_py_z6-20131230163449.shp E:\code\Spatial\Connections\OPS$GEODATA_D2CS01.sde\GEO2013_TRACT_P2G3_A TEST # #</Process><Process ToolSource="E:\Program Files (x86)\ArcGIS\Desktop10.0\ArcToolbox\Toolboxes\Data Management Tools.tbx\Append" Date="20140102" Time="212235">Append G:\load\en\GEO\2013\spatial\geo_2013_g_48000_140_00_py_z6-20131230163449.shp E:\code\Spatial\Connections\OPS$GEODATA_D2CS01.sde\GEO2013_TRACT_P2G3_A TEST # #</Process><Process ToolSource="E:\Program Files (x86)\ArcGIS\Desktop10.0\ArcToolbox\Toolboxes\Data Management Tools.tbx\Append" Date="20140102" Time="212644">Append G:\load\en\GEO\2013\spatial\geo_2013_g_32000_140_00_py_z6-20131230163449.shp E:\code\Spatial\Connections\OPS$GEODATA_D2CS01.sde\GEO2013_TRACT_P2G3_A TEST # #</Process><Process ToolSource="E:\Program Files (x86)\ArcGIS\Desktop10.0\ArcToolbox\Toolboxes\Data Management Tools.tbx\Append" Date="20140102" Time="212905">Append G:\load\en\GEO\2013\spatial\geo_2013_g_44000_140_00_py_z6-20131230163449.shp E:\code\Spatial\Connections\OPS$GEODATA_D2CS01.sde\GEO2013_TRACT_P2G3_A TEST # #</Process><Process ToolSource="E:\Program Files (x86)\ArcGIS\Desktop10.0\ArcToolbox\Toolboxes\Data Management Tools.tbx\Append" Date="20140102" Time="214227">Append G:\load\en\GEO\2013\spatial\geo_2013_g_51000_140_00_py_z6-20131230163449.shp E:\code\Spatial\Connections\OPS$GEODATA_D2CS01.sde\GEO2013_TRACT_P2G3_A TEST # #</Process><Process ToolSource="E:\Program Files (x86)\ArcGIS\Desktop10.0\ArcToolbox\Toolboxes\Data Management Tools.tbx\Append" Date="20140102" Time="215220">Append G:\load\en\GEO\2013\spatial\geo_2013_g_54000_140_00_py_z6-20131230163449.shp E:\code\Spatial\Connections\OPS$GEODATA_D2CS01.sde\GEO2013_TRACT_P2G3_A TEST # #</Process><Process ToolSource="E:\Program Files (x86)\ArcGIS\Desktop10.0\ArcToolbox\Toolboxes\Data Management Tools.tbx\Append" Date="20140102" Time="215410">Append G:\load\en\GEO\2013\spatial\geo_2013_g_49000_140_00_py_z6-20131230163449.shp E:\code\Spatial\Connections\OPS$GEODATA_D2CS01.sde\GEO2013_TRACT_P2G3_A TEST # #</Process><Process ToolSource="E:\Program Files (x86)\ArcGIS\Desktop10.0\ArcToolbox\Toolboxes\Data Management Tools.tbx\Append" Date="20140102" Time="215850">Append G:\load\en\GEO\2013\spatial\geo_2013_g_17000_140_00_py_z6-20131230163449.shp E:\code\Spatial\Connections\OPS$GEODATA_D2CS01.sde\GEO2013_TRACT_P2G3_A TEST # #</Process><Process ToolSource="E:\Program Files (x86)\ArcGIS\Desktop10.0\ArcToolbox\Toolboxes\Data Management Tools.tbx\Append" Date="20140102" Time="221256">Append G:\load\en\GEO\2013\spatial\geo_2013_g_20000_140_00_py_z6-20131230163449.shp E:\code\Spatial\Connections\OPS$GEODATA_D2CS01.sde\GEO2013_TRACT_P2G3_A TEST # #</Process><Process ToolSource="E:\Program Files (x86)\ArcGIS\Desktop10.0\ArcToolbox\Toolboxes\Data Management Tools.tbx\Append" Date="20140102" Time="222937">Append G:\load\en\GEO\2013\spatial\geo_2013_g_13000_140_00_py_z6-20131230163449.shp E:\code\Spatial\Connections\OPS$GEODATA_D2CS01.sde\GEO2013_TRACT_P2G3_A TEST # #</Process><Process ToolSource="E:\Program Files (x86)\ArcGIS\Desktop10.0\ArcToolbox\Toolboxes\Data Management Tools.tbx\Append" Date="20140102" Time="223053">Append G:\load\en\GEO\2013\spatial\geo_2013_g_39000_140_00_py_z6-20131230163449.shp E:\code\Spatial\Connections\OPS$GEODATA_D2CS01.sde\GEO2013_TRACT_P2G3_A TEST # #</Process><Process ToolSource="E:\Program Files (x86)\ArcGIS\Desktop10.0\ArcToolbox\Toolboxes\Data Management Tools.tbx\Append" Date="20140102" Time="223341">Append G:\load\en\GEO\2013\spatial\geo_2013_g_23000_140_00_py_z6-20131230163449.shp E:\code\Spatial\Connections\OPS$GEODATA_D2CS01.sde\GEO2013_TRACT_P2G3_A TEST # #</Process><Process ToolSource="E:\Program Files (x86)\ArcGIS\Desktop10.0\ArcToolbox\Toolboxes\Data Management Tools.tbx\Append" Date="20140102" Time="223954">Append G:\load\en\GEO\2013\spatial\geo_2013_g_40000_140_00_py_z6-20131230163449.shp E:\code\Spatial\Connections\OPS$GEODATA_D2CS01.sde\GEO2013_TRACT_P2G3_A TEST # #</Process><Process ToolSource="E:\Program Files (x86)\ArcGIS\Desktop10.0\ArcToolbox\Toolboxes\Data Management Tools.tbx\Append" Date="20140102" Time="224218">Append G:\load\en\GEO\2013\spatial\geo_2013_g_11000_140_00_py_z6-20131230163449.shp E:\code\Spatial\Connections\OPS$GEODATA_D2CS01.sde\GEO2013_TRACT_P2G3_A TEST # #</Process><Process ToolSource="E:\Program Files (x86)\ArcGIS\Desktop10.0\ArcToolbox\Toolboxes\Data Management Tools.tbx\Append" Date="20140102" Time="224353">Append G:\load\en\GEO\2013\spatial\geo_2013_g_04000_140_00_py_z6-20131230163449.shp E:\code\Spatial\Connections\OPS$GEODATA_D2CS01.sde\GEO2013_TRACT_P2G3_A TEST # #</Process><Process ToolSource="E:\Program Files (x86)\ArcGIS\Desktop10.0\ArcToolbox\Toolboxes\Data Management Tools.tbx\Append" Date="20140102" Time="225151">Append G:\load\en\GEO\2013\spatial\geo_2013_g_37000_140_00_py_z6-20131230163449.shp E:\code\Spatial\Connections\OPS$GEODATA_D2CS01.sde\GEO2013_TRACT_P2G3_A TEST # #</Process><Process ToolSource="E:\Program Files (x86)\ArcGIS\Desktop10.0\ArcToolbox\Toolboxes\Data Management Tools.tbx\Append" Date="20140102" Time="225406">Append G:\load\en\GEO\2013\spatial\geo_2013_g_27000_140_00_py_z6-20131230163449.shp E:\code\Spatial\Connections\OPS$GEODATA_D2CS01.sde\GEO2013_TRACT_P2G3_A TEST # #</Process><Process ToolSource="E:\Program Files (x86)\ArcGIS\Desktop10.0\ArcToolbox\Toolboxes\Data Management Tools.tbx\Append" Date="20140102" Time="230435">Append G:\load\en\GEO\2013\spatial\geo_2013_g_72000_140_00_py_z6-20131230163449.shp E:\code\Spatial\Connections\OPS$GEODATA_D2CS01.sde\GEO2013_TRACT_P2G3_A TEST # #</Process><Process ToolSource="E:\Program Files (x86)\ArcGIS\Desktop10.0\ArcToolbox\Toolboxes\Data Management Tools.tbx\Append" Date="20140102" Time="231203">Append G:\load\en\GEO\2013\spatial\geo_2013_g_28000_140_00_py_z6-20131230163449.shp E:\code\Spatial\Connections\OPS$GEODATA_D2CS01.sde\GEO2013_TRACT_P2G3_A TEST # #</Process><Process ToolSource="E:\Program Files (x86)\ArcGIS\Desktop10.0\ArcToolbox\Toolboxes\Data Management Tools.tbx\Append" Date="20140102" Time="232257">Append G:\load\en\GEO\2013\spatial\geo_2013_g_56000_140_00_py_z6-20131230163449.shp E:\code\Spatial\Connections\OPS$GEODATA_D2CS01.sde\GEO2013_TRACT_P2G3_A TEST # #</Process><Process ToolSource="E:\Program Files (x86)\ArcGIS\Desktop10.0\ArcToolbox\Toolboxes\Data Management Tools.tbx\Append" Date="20140102" Time="232719">Append G:\load\en\GEO\2013\spatial\geo_2013_g_09000_140_00_py_z6-20131230163449.shp E:\code\Spatial\Connections\OPS$GEODATA_D2CS01.sde\GEO2013_TRACT_P2G3_A TEST # #</Process><Process ToolSource="E:\Program Files (x86)\ArcGIS\Desktop10.0\ArcToolbox\Toolboxes\Data Management Tools.tbx\Append" Date="20140102" Time="235502">Append G:\load\en\GEO\2013\spatial\geo_2013_g_46000_140_00_py_z6-20131230163449.shp E:\code\Spatial\Connections\OPS$GEODATA_D2CS01.sde\GEO2013_TRACT_P2G3_A TEST # #</Process><Process ToolSource="E:\Program Files (x86)\ArcGIS\Desktop10.0\ArcToolbox\Toolboxes\Data Management Tools.tbx\Append" Date="20140103" Time="000725">Append G:\load\en\GEO\2013\spatial\geo_2013_g_66000_140_00_py_z6-20131230163449.shp E:\code\Spatial\Connections\OPS$GEODATA_D2CS01.sde\GEO2013_TRACT_P2G3_A TEST # #</Process><Process ToolSource="E:\Program Files (x86)\ArcGIS\Desktop10.0\ArcToolbox\Toolboxes\Data Management Tools.tbx\Append" Date="20140103" Time="001150">Append G:\load\en\GEO\2013\spatial\geo_2013_g_55000_140_00_py_z6-20131230163449.shp E:\code\Spatial\Connections\OPS$GEODATA_D2CS01.sde\GEO2013_TRACT_P2G3_A TEST # #</Process><Process ToolSource="E:\Program Files (x86)\ArcGIS\Desktop10.0\ArcToolbox\Toolboxes\Data Management Tools.tbx\Append" Date="20140103" Time="002950">Append G:\load\en\GEO\2013\spatial\geo_2013_g_25000_140_00_py_z6-20131230163449.shp E:\code\Spatial\Connections\OPS$GEODATA_D2CS01.sde\GEO2013_TRACT_P2G3_A TEST # #</Process><Process ToolSource="E:\Program Files (x86)\ArcGIS\Desktop10.0\ArcToolbox\Toolboxes\Data Management Tools.tbx\Append" Date="20140103" Time="003201">Append G:\load\en\GEO\2013\spatial\geo_2013_g_47000_140_00_py_z6-20131230163449.shp E:\code\Spatial\Connections\OPS$GEODATA_D2CS01.sde\GEO2013_TRACT_P2G3_A TEST # #</Process><Process ToolSource="E:\Program Files (x86)\ArcGIS\Desktop10.0\ArcToolbox\Toolboxes\Data Management Tools.tbx\Append" Date="20140103" Time="003911">Append G:\load\en\GEO\2013\spatial\geo_2013_g_34000_140_00_py_z6-20131230163449.shp E:\code\Spatial\Connections\OPS$GEODATA_D2CS01.sde\GEO2013_TRACT_P2G3_A TEST # #</Process><Process ToolSource="E:\Program Files (x86)\ArcGIS\Desktop10.0\ArcToolbox\Toolboxes\Data Management Tools.tbx\Append" Date="20140103" Time="004739">Append G:\load\en\GEO\2013\spatial\geo_2013_g_24000_140_00_py_z6-20131230163449.shp E:\code\Spatial\Connections\OPS$GEODATA_D2CS01.sde\GEO2013_TRACT_P2G3_A TEST # #</Process><Process ToolSource="E:\Program Files (x86)\ArcGIS\Desktop10.0\ArcToolbox\Toolboxes\Data Management Tools.tbx\Append" Date="20140103" Time="010115">Append G:\load\en\GEO\2013\spatial\geo_2013_g_50000_140_00_py_z6-20131230163449.shp E:\code\Spatial\Connections\OPS$GEODATA_D2CS01.sde\GEO2013_TRACT_P2G3_A TEST # #</Process><Process ToolSource="E:\Program Files (x86)\ArcGIS\Desktop10.0\ArcToolbox\Toolboxes\Data Management Tools.tbx\Append" Date="20140103" Time="010627">Append G:\load\en\GEO\2013\spatial\geo_2013_g_35000_140_00_py_z6-20131230163449.shp E:\code\Spatial\Connections\OPS$GEODATA_D2CS01.sde\GEO2013_TRACT_P2G3_A TEST # #</Process><Process ToolSource="E:\Program Files (x86)\ArcGIS\Desktop10.0\ArcToolbox\Toolboxes\Data Management Tools.tbx\Append" Date="20140103" Time="011353">Append G:\load\en\GEO\2013\spatial\geo_2013_g_31000_140_00_py_z6-20131230163449.shp E:\code\Spatial\Connections\OPS$GEODATA_D2CS01.sde\GEO2013_TRACT_P2G3_A TEST # #</Process><Process ToolSource="E:\Program Files (x86)\ArcGIS\Desktop10.0\ArcToolbox\Toolboxes\Data Management Tools.tbx\Append" Date="20140103" Time="013807">Append G:\load\en\GEO\2013\spatial\geo_2013_g_53000_140_00_py_z6-20131230163449.shp E:\code\Spatial\Connections\OPS$GEODATA_D2CS01.sde\GEO2013_TRACT_P2G3_A TEST # #</Process><Process ToolSource="E:\Program Files (x86)\ArcGIS\Desktop10.0\ArcToolbox\Toolboxes\Data Management Tools.tbx\Append" Date="20140103" Time="015645">Append G:\load\en\GEO\2013\spatial\geo_2013_g_45000_140_00_py_z6-20131230163449.shp E:\code\Spatial\Connections\OPS$GEODATA_D2CS01.sde\GEO2013_TRACT_P2G3_A TEST # #</Process><Process ToolSource="E:\Program Files (x86)\ArcGIS\Desktop10.0\ArcToolbox\Toolboxes\Data Management Tools.tbx\Append" Date="20140103" Time="015722">Append G:\load\en\GEO\2013\spatial\geo_2013_g_26000_140_00_py_z6-20131230163449.shp E:\code\Spatial\Connections\OPS$GEODATA_D2CS01.sde\GEO2013_TRACT_P2G3_A TEST # #</Process><Process ToolSource="E:\Program Files (x86)\ArcGIS\Desktop10.0\ArcToolbox\Toolboxes\Data Management Tools.tbx\Append" Date="20140103" Time="015954">Append G:\load\en\GEO\2013\spatial\geo_2013_g_08000_140_00_py_z6-20131230163449.shp E:\code\Spatial\Connections\OPS$GEODATA_D2CS01.sde\GEO2013_TRACT_P2G3_A TEST # #</Process><Process ToolSource="E:\Program Files (x86)\ArcGIS\Desktop10.0\ArcToolbox\Toolboxes\Data Management Tools.tbx\Append" Date="20140103" Time="020025">Append G:\load\en\GEO\2013\spatial\geo_2013_g_33000_140_00_py_z6-20131230163449.shp E:\code\Spatial\Connections\OPS$GEODATA_D2CS01.sde\GEO2013_TRACT_P2G3_A TEST # #</Process><Process ToolSource="E:\Program Files (x86)\ArcGIS\Desktop10.0\ArcToolbox\Toolboxes\Data Management Tools.tbx\Append" Date="20140103" Time="020701">Append G:\load\en\GEO\2013\spatial\geo_2013_g_36000_140_00_py_z6-20131230163449.shp E:\code\Spatial\Connections\OPS$GEODATA_D2CS01.sde\GEO2013_TRACT_P2G3_A TEST # #</Process><Process ToolSource="E:\Program Files (x86)\ArcGIS\Desktop10.0\ArcToolbox\Toolboxes\Data Management Tools.tbx\Append" Date="20140103" Time="023332">Append G:\load\en\GEO\2013\spatial\geo_2013_g_29000_140_00_py_z6-20131230163449.shp E:\code\Spatial\Connections\OPS$GEODATA_D2CS01.sde\GEO2013_TRACT_P2G3_A TEST # #</Process><Process ToolSource="E:\Program Files (x86)\ArcGIS\Desktop10.0\ArcToolbox\Toolboxes\Data Management Tools.tbx\Append" Date="20140103" Time="025038">Append G:\load\en\GEO\2013\spatial\geo_2013_g_41000_140_00_py_z6-20131230163449.shp E:\code\Spatial\Connections\OPS$GEODATA_D2CS01.sde\GEO2013_TRACT_P2G3_A TEST # #</Process><Process ToolSource="E:\Program Files (x86)\ArcGIS\Desktop10.0\ArcToolbox\Toolboxes\Data Management Tools.tbx\Append" Date="20140103" Time="025201">Append G:\load\en\GEO\2013\spatial\geo_2013_g_42000_140_00_py_z6-20131230163449.shp E:\code\Spatial\Connections\OPS$GEODATA_D2CS01.sde\GEO2013_TRACT_P2G3_A TEST # #</Process><Process ToolSource="E:\Program Files (x86)\ArcGIS\Server10.0\ArcToolbox\Toolboxes\Analysis Tools.tbx\Select" Date="20150402" Time="180150">Select E:\ags_connections\ops$geodata@d2es_rac_taf.sde\GEO2013_TRACT_P2G3_A E:\arcgisserver\arcgisjobs\download_shape_gpserver\j4da1b4d9262c4dd7a12e8fe58b91a1fb\scratch\EUS0.shp "GEO_ID IN ('1400000US17031842900','1400000US17043841503','1400000US17167001001','1400000US17043841504','1400000US17177000200','1400000US17167001003','1400000US17143003800','1400000US17167001004','1400000US17031480400','1400000US17115000300','1400000US17201001900','1400000US17031815300','1400000US17117956200','1400000US17141961500','1400000US17031051100','1400000US17097861603','1400000US17097861604','1400000US17031031501','1400000US17119401200','1400000US17031031502','1400000US17031580600','1400000US17097861607','1400000US17097861608','1400000US17097861609','1400000US17031802002','1400000US17031802003','1400000US17031802004','1400000US17181950300','1400000US17031400300','1400000US17097861610','1400000US17001001001','1400000US17097861611','1400000US17001001002','1400000US17111870401','1400000US17111870402','1400000US17031827300','1400000US17031807700','1400000US17031520100','1400000US17089854200','1400000US17043840201','1400000US17031841600','1400000US17043840202','1400000US17075950700','1400000US17031063100','1400000US17143002500','1400000US17031251500','1400000US17103000400','1400000US17201000600','1400000US17031190900','1400000US17031814000','1400000US17031620300','1400000US17081051100','1400000US17031600700','1400000US17163502800','1400000US17043845901','1400000US17097860301','1400000US17043845902','1400000US17097860302','1400000US17031030200','1400000US17031010600','1400000US17033880600','1400000US17031819700','1400000US17031740100','1400000US17031720500','1400000US17031283100','1400000US17031491100','1400000US17031826000','1400000US17031806400','1400000US17031840300','1400000US17031820700','1400000US17143001200','1400000US17031250200','1400000US17031230600','1400000US17109011000','1400000US17019010601','1400000US17019010603','1400000US17019010604','1400000US17031411000','1400000US17165955500','1400000US17043844601','1400000US17163501501','1400000US17043844602','1400000US17137952000','1400000US17163501502','1400000US17031350400','1400000US17035972600','1400000US17031691500','1400000US17031671900','1400000US17037001600','1400000US17031081800','1400000US17031838000','1400000US17031818401','1400000US17031818402','1400000US17097864700','1400000US17031242600','1400000US17073030800','1400000US17039971800','1400000US17031805105','1400000US17031805106','1400000US17031805107','1400000US17031805108','1400000US17031805109','1400000US17095001000','1400000US17031611400','1400000US17099964300','1400000US17051950900','1400000US17031570400','1400000US17203030700','1400000US17031805110','1400000US17031805111','1400000US17031805112','1400000US17173959300','1400000US17067954000','1400000US17043843301','1400000US17043843302','1400000US17025972100','1400000US17115002100','1400000US17031670600','1400000US17037000300','1400000US17201003705','1400000US17201003706','1400000US17031060900','1400000US17201003707','1400000US17201003708','1400000US17201003709','1400000US17031817101','1400000US17031817102','1400000US17031831400','1400000US17087977700','1400000US17097863400','1400000US17031811800','1400000US17031241300','1400000US17119403001','1400000US17119403002','1400000US17201003710','1400000US17031770800','1400000US17107953500','1400000US17201003711','1400000US17029000900','1400000US17099963000','1400000US17093890500','1400000US17105960400','1400000US17031280900','1400000US17031829100','1400000US17031809500','1400000US17043842000','1400000US17031710300','1400000US17031843400','1400000US17031823801','1400000US17143004300','1400000US17031823803','1400000US17031120200','1400000US17031823805','1400000US17031100600','1400000US17031823806','1400000US17085020500','1400000US17187870500','1400000US17161022900','1400000US17201002400','1400000US17089850701','1400000US17089850702','1400000US17089850703','1400000US17113001402','1400000US17113001403','1400000US17113001404','1400000US17031830100','1400000US17097862100','1400000US17163504600','1400000US17031810501','1400000US17031810502','1400000US17125956500','1400000US17031220400','1400000US17057953900','1400000US17127970200','1400000US17179020100','1400000US17167001900','1400000US17019000401','1400000US17019000402','1400000US17031835800','1400000US17159978200','1400000US17031681300','1400000US17031320600','1400000US17197881700','1400000US17031071600','1400000US17031808200','1400000US17031842100','1400000US17031822500','1400000US17031802900','1400000US17143003000','1400000US17031252000','1400000US17013951300','1400000US17161021600','1400000US17201001100','1400000US17031420800','1400000US17113000102','1400000US17113000104','1400000US17113000105','1400000US17163503301','1400000US17043846404','1400000US17163503304','1400000US17043846405','1400000US17091011600','1400000US17003957800','1400000US17031560200','1400000US17043846408','1400000US17043846409','1400000US17113005800','1400000US17167000600','1400000US17031291600','1400000US17043846410','1400000US17043846411','1400000US17031834500','1400000US17043846412','1400000US17043846413','1400000US17031814900','1400000US17031660400','1400000US17031640800','1400000US17197880404','1400000US17031070300','1400000US17149952800','1400000US17031050700','1400000US17197880408','1400000US17119400801','1400000US17119400802','1400000US17031821200','1400000US17163503322','1400000US17163503323','1400000US17163503324','1400000US17031801601','1400000US17031801603','1400000US17031231100','1400000US17031801605','1400000US17031801606','1400000US17161020300','1400000US17031801607','1400000US17063000500','1400000US17197880410','1400000US17031801608','1400000US17197880411','1400000US17197880412','1400000US17197880414','1400000US17001000600','1400000US17031190100','1400000US17197880415','1400000US17197880416','1400000US17019011100','1400000US17031170500','1400000US17197880417','1400000US17197880418','1400000US17197880419','1400000US17165956000','1400000US17043845100','1400000US17163503332','1400000US17163503334','1400000US17031826901','1400000US17091010300','1400000US17031826902','1400000US17197880420','1400000US17197880421','1400000US17037002100','1400000US17055040300','1400000US17031062700','1400000US17031700100','1400000US17097865200','1400000US17031813600','1400000US17031243100','1400000US17183010500','1400000US17081050700','1400000US17031390500','1400000US17031800300','1400000US17041952200','1400000US17031282700','1400000US17031490700','1400000US17077010900','1400000US17193958200','1400000US17031825600','1400000US17031671100','1400000US17031310400','1400000US17201004200','1400000US17089852500','1400000US17195001500','1400000US17031081000','1400000US17109010600','1400000US17031812301','1400000US17031812302','1400000US17135957500','1400000US17031222200','1400000US17031430200','1400000US17031410600','1400000US17137951600','1400000US17167003700','1400000US17199020300','1400000US17049950600','1400000US17031530400','1400000US17197883504','1400000US17015960500','1400000US17197883505','1400000US17197883507','1400000US17197883509','1400000US17021958200','1400000US17031824300','1400000US17031804701','1400000US17031804705','1400000US17031650200','1400000US17031804706','1400000US17121952500','1400000US17195000200','1400000US17197883510','1400000US17197883511','1400000US17031804709','1400000US17095000600','1400000US17099963900','1400000US17197883513','1400000US17131040100','1400000US17197883514','1400000US17031060100','1400000US17197883515','1400000US17197883516','1400000US17197883517','1400000US17197883519','1400000US17031020901','1400000US17031020902','1400000US17031811000','1400000US17031804710','1400000US17185957500','1400000US17031804711','1400000US17031804712','1400000US17031804713','1400000US17031804714','1400000US17031804715','1400000US17031804716','1400000US17155954600','1400000US17031750400','1400000US17197883521','1400000US17197883522','1400000US17043842900','1400000US17167002400','1400000US17031160300','1400000US17029000100','1400000US17031140701','1400000US17031140702','1400000US17115001700','1400000US17031836300','1400000US17031816700','1400000US17079977500','1400000US17197882200','1400000US17053961900','1400000US17031280100','1400000US17031260500','1400000US17031240900','1400000US17119402600','1400000US17031823001','1400000US17031803400','1400000US17031823002','1400000US17161022100','1400000US17183000300','1400000US17099962600','1400000US17045070500','1400000US17031828701','1400000US17091012100','1400000US17031828702','1400000US17057953100','1400000US17167001100','1400000US17043841603','1400000US17043841604','1400000US17177000300','1400000US17043841605','1400000US17043841606','1400000US17143003900','1400000US17031480500','1400000US17043841607','1400000US17115000400','1400000US17031835000','1400000US17031815400','1400000US17117956300','1400000US17141961600','1400000US17097861701','1400000US17031051200','1400000US17097861702','1400000US17019005300','1400000US17119401300','1400000US17031580700','1400000US17031802100','1400000US17181950400','1400000US17031400400','1400000US17001001100','1400000US17031171000','1400000US17111870500','1400000US17031680900','1400000US17031827400','1400000US17031807800','1400000US17031520200','1400000US17089854301','1400000US17089854302','1400000US17031841700','1400000US17043840303','1400000US17043840304','1400000US17075950800','1400000US17031063200','1400000US17031271200','1400000US17143002600','1400000US17031251600','1400000US17103000500','1400000US17201000700','1400000US17031814100','1400000US17183011000','1400000US17031620400','1400000US17097860400','1400000US17163502900','1400000US17031030300','1400000US17031010701','1400000US17031010702','1400000US17031819801','1400000US17031819802','1400000US17031740200','1400000US17031720600','1400000US17031283200','1400000US17031491200','1400000US17077011400','1400000US17031826100','1400000US17031806501','1400000US17031806502','1400000US17089853001','1400000US17031840400','1400000US17089853004','1400000US17031820800','1400000US17089853005','1400000US17089853006','1400000US17089853007','1400000US17143001300','1400000US17089853008','1400000US17031250300','1400000US17031230700','1400000US17109011100','1400000US17019010700','1400000US17135958000','1400000US17047957000','1400000US17031411100','1400000US17083010100','1400000US17165955600','1400000US17043844701','1400000US17043844702','1400000US17137952100','1400000US17163501602','1400000US17163501603','1400000US17163501604','1400000US17163501605','1400000US17157950500','1400000US17037001700','1400000US17031081900','1400000US17031838100','1400000US17031818500','1400000US17197884003','1400000US17197884004','1400000US17197884005','1400000US17097864801','1400000US17197884006','1400000US17077010100','1400000US17097864802','1400000US17031242700','1400000US17073030900','1400000US17031805201','1400000US17031805202','1400000US17095001100','1400000US17031611500','1400000US17031570500','1400000US17173959400','1400000US17067954100','1400000US17043843400','1400000US17025972200','1400000US17031690300','1400000US17115002200','1400000US17031670700','1400000US17037000400','1400000US17201003801','1400000US17201003805','1400000US17201003806','1400000US17201003807','1400000US17201003808','1400000US17201003809','1400000US17031817200','1400000US17031831500','1400000US17087977800','1400000US17097863500','1400000US17031811900','1400000US17031261000','1400000US17031241400','1400000US17119403101','1400000US17107953600','1400000US17031770901','1400000US17031770902','1400000US17179021500','1400000US17099963100','1400000US17031020100','1400000US17093890600','1400000US17105960500','1400000US17031829200','1400000US17031809600','1400000US17043842100','1400000US17031710400') OR GEO_ID IN ('1400000US17031843500','1400000US17031823901','1400000US17143004400','1400000US17031823903','1400000US17031120300','1400000US17031823904','1400000US17119403121','1400000US17119403122','1400000US17031100700','1400000US17089850800','1400000US17201002500','1400000US17113001500','1400000US17031830201','1400000US17097862200','1400000US17031810600','1400000US17031830202','1400000US17031032100','1400000US17125956600','1400000US17031220500','1400000US17127970300','1400000US17019000500','1400000US17031835900','1400000US17159978300','1400000US17031340300','1400000US17111871003','1400000US17031681400','1400000US17111871004','1400000US17145030100','1400000US17197881800','1400000US17031071700','1400000US17031808301','1400000US17031808302','1400000US17031842200','1400000US17031822601','1400000US17031822602','1400000US17143003101','1400000US17143003102','1400000US17031252101','1400000US17031460100','1400000US17031252102','1400000US17161021700','1400000US17201001200','1400000US17113000200','1400000US17163503402','1400000US17043846504','1400000US17163503404','1400000US17091011700','1400000US17003957900','1400000US17043846507','1400000US17031560300','1400000US17043846509','1400000US17113005900','1400000US17167000700','1400000US17043846510','1400000US17043846511','1400000US17163503411','1400000US17031834600','1400000US17163503412','1400000US17043846513','1400000US17163503413','1400000US17043846514','1400000US17163503414','1400000US17043846515','1400000US17043846517','1400000US17043846518','1400000US17043846519','1400000US17031660500','1400000US17197880502','1400000US17197880503','1400000US17031070400','1400000US17197880505','1400000US17031050800','1400000US17197880507','1400000US17031807000','1400000US17119400903','1400000US17119400904','1400000US17043846521','1400000US17031821300','1400000US17043846522','1400000US17043846523','1400000US17043846524','1400000US17031801701','1400000US17031801702','1400000US17031231200','1400000US17161020400','1400000US17063000600','1400000US17001000700','1400000US17031190200','1400000US17031170600','1400000US17165956100','1400000US17043845200','1400000US17163502100','1400000US17091010400','1400000US17157951000','1400000US17031351000','1400000US17037002200','1400000US17089853900','1400000US17055040400','1400000US17031062800','1400000US17031819000','1400000US17031700200','1400000US17031833300','1400000US17097865300','1400000US17031813701','1400000US17031813702','1400000US17031110100','1400000US17031243200','1400000US17183010600','1400000US17081050800','1400000US17031390600','1400000US17031612000','1400000US17031820000','1400000US17031800400','1400000US17041952300','1400000US17031282800','1400000US17031490800','1400000US17193958300','1400000US17031825700','1400000US17031330100','1400000US17031671200','1400000US17031310500','1400000US17201004300','1400000US17195001600','1400000US17089852601','1400000US17031081100','1400000US17031061500','1400000US17089852606','1400000US17143000900','1400000US17119400951','1400000US17119400952','1400000US17109010700','1400000US17031832000','1400000US17031812400','1400000US17097864001','1400000US17097864002','1400000US17135957600','1400000US17031430300','1400000US17073030100','1400000US17031410700','1400000US17179022000','1400000US17137951700','1400000US17199020400','1400000US17049950700','1400000US17167003801','1400000US17167003802','1400000US17031550100','1400000US17031530501','1400000US17105961000','1400000US17031530502','1400000US17031530503','1400000US17197883602','1400000US17197883603','1400000US17015960600','1400000US17197883605','1400000US17197883606','1400000US17021958300','1400000US17031824400','1400000US17031804803','1400000US17031804804','1400000US17031804805','1400000US17031804806','1400000US17121952600','1400000US17161023500','1400000US17195000300','1400000US17201003000','1400000US17031650301','1400000US17031804807','1400000US17089851301','1400000US17031650302','1400000US17031804808','1400000US17089851302','1400000US17031804809','1400000US17095000700','1400000US17131040200','1400000US17031060200','1400000US17031040600','1400000US17031811100','1400000US17031804810','1400000US17031221000','1400000US17031750500','1400000US17067953700','1400000US17001010100','1400000US17167002500','1400000US17019001000','1400000US17031160400','1400000US17029000200','1400000US17031140800','1400000US17115001801','1400000US17115001802','1400000US17031836400','1400000US17031816800','1400000US17031301600','1400000US17197882300','1400000US17031260600','1400000US17119402701','1400000US17031823101','1400000US17031803500','1400000US17031823102','1400000US17161022200','1400000US17183000400','1400000US17099962700','1400000US17031828801','1400000US17091012200','1400000US17031828802','1400000US17031200100','1400000US17057953200','1400000US17167001200','1400000US17043841703','1400000US17031292200','1400000US17043841704','1400000US17177000400','1400000US17043841705','1400000US17043841706','1400000US17119402721','1400000US17115000500','1400000US17119402722','1400000US17031835100','1400000US17031815500','1400000US17031661000','1400000US17197881001','1400000US17197881002','1400000US17117956400','1400000US17141961700','1400000US17197881005','1400000US17197881006','1400000US17031051300','1400000US17197881007','1400000US17097861803','1400000US17031031700','1400000US17097861804','1400000US17197881009','1400000US17019005401','1400000US17119401400','1400000US17019005402','1400000US17031580800','1400000US17191955000','1400000US17031802200','1400000US17181950500','1400000US17031420100','1400000US17197881010','1400000US17197881011','1400000US17031400500','1400000US17197881012','1400000US17031171100','1400000US17159977900','1400000US17111870603','1400000US17111870604','1400000US17111870605','1400000US17111870606','1400000US17031827500','1400000US17031807900','1400000US17031520300','1400000US17089854400','1400000US17113005101','1400000US17031841800','1400000US17113005102','1400000US17005951200','1400000US17075950900','1400000US17031063301','1400000US17031271300','1400000US17031063302','1400000US17143002701','1400000US17031063303','1400000US17031251700','1400000US17143002702','1400000US17103000600','1400000US17201000800','1400000US17031814200','1400000US17031640100','1400000US17183011100','1400000US17031600900','1400000US17097860500','1400000US17169970100','1400000US17031030400','1400000US17119400101','1400000US17119400102','1400000US17031839500','1400000US17031819900','1400000US17031740300','1400000US17031720700','1400000US17031150200','1400000US17031491300','1400000US17031826201','1400000US17031806600','1400000US17031826202','1400000US17089853100','1400000US17153971000','1400000US17031062000','1400000US17031820901','1400000US17031820902','1400000US17031250400','1400000US17031230800','1400000US17019010800','1400000US17047957100','1400000US17031411200','1400000US17083010200','1400000US17165955700','1400000US17163501700','1400000US17043844801','1400000US17043844802','1400000US17137952200','1400000US17157950600','1400000US17037001800','1400000US17031838200','1400000US17031818600','1400000US17197884101','1400000US17197884103','1400000US17031832900','1400000US17097864901','1400000US17077010200','1400000US17097864903','1400000US17097864904','1400000US17031242800','1400000US17031805301','1400000US17031805302','1400000US17161024000','1400000US17095001200','1400000US17031611600','1400000US17143000100','1400000US17173959500','1400000US17067954200','1400000US17043843500','1400000US17163500400','1400000US17167003000','1400000US17031690400','1400000US17115002300','1400000US17031670800','1400000US17037000500','1400000US17201003901','1400000US17201003903','1400000US17201003904','1400000US17031817300','1400000US17031510100','1400000US17031831600','1400000US17097863601','1400000US17097863603','1400000US17097863604','1400000US17031241500','1400000US17119403200','1400000US17179021603','1400000US17179021604','1400000US17179021605','1400000US17179021606','1400000US17031804000','1400000US17031610300','1400000US17099963200','1400000US17031020200','1400000US17093890700','1400000US17105960600','1400000US17031829301','1400000US17031809700','1400000US17031829302','1400000US17031730100','1400000US17043842200','1400000US17065973100','1400000US17031710500','1400000US17031843600','1400000US17143004500','1400000US17031120400','1400000US17115001000','1400000US17201002600','1400000US17113001600','1400000US17031816000','1400000US17011965000','1400000US17031830300','1400000US17097862300','1400000US17031810701','1400000US17031810702','1400000US17125956700','1400000US17147954500','1400000US17031240200','1400000US17031220601','1400000US17031220602','1400000US17127970400','1400000US17179020301','1400000US17179020302','1400000US17031340400','1400000US17111871104','1400000US17111871105','1400000US17111871106','1400000US17111871107','1400000US17145030200','1400000US17197881900','1400000US17111871108','1400000US17111871109','1400000US17031071800','1400000US17031828000','1400000US17031808400','1400000US17031842300','1400000US17031822701','1400000US17031822702','1400000US17143003200','1400000US17031252201','1400000US17031460200','1400000US17031252202','1400000US17031440600','1400000US17161021800','1400000US17201001300','1400000US17113000301','1400000US17113000302','1400000US17043846603','1400000US17043846604','1400000US17069971000','1400000US17091011800','1400000US17097861007','1400000US17031560400','1400000US17097861008','1400000US17057952800','1400000US17097861009','1400000US17167000800','1400000US17097861010','1400000US17097861011','1400000US17031834700','1400000US17097861012','1400000US17097861013','1400000US17097861014','1400000US17031660600','1400000US17197880601','1400000US17197880602','1400000US17031090100','1400000US17031070500','1400000US17031050900','1400000US17031807100','1400000US17031841000','1400000US17075950100','1400000US17031821401','1400000US17031801800','1400000US17031821402','1400000US17063000700','1400000US17031760801','1400000US17031760802','1400000US17031760803','1400000US17001000800','1400000US17031190300','1400000US17129010100','1400000US17031170700','1400000US17165956200','1400000US17043845300','1400000US17163502200','1400000US17091010500','1400000US17157951100','1400000US17031351100','1400000US17055040500','1400000US17031062900','1400000US17031819100','1400000US17031700301','1400000US17097865400','1400000US17031700302','1400000US17031813801','1400000US17031813802','1400000US17031110200','1400000US17031243300','1400000US17183010701','1400000US17183010702','1400000US17081050900','1400000US17031390700','1400000US17031612100','1400000US17031820101','1400000US17031800500','1400000US17041952400','1400000US17031820103','1400000US17031820104','1400000US17031210400','1400000US17031490901','1400000US17031490902','1400000US17193958400','1400000US17043844001','1400000US17043844002','1400000US17031825801','1400000US17031825802','1400000US17031825803','1400000US17031330200','1400000US17031671300','1400000US17031310600','1400000US17089852700','1400000US17195001700','1400000US17037001001','1400000US17037001002','1400000US17031081201','1400000US17031081202','1400000US17031832100','1400000US17031812500','1400000US17097864101','1400000US17027900100','1400000US17031242000','1400000US17097864105','1400000US17097864106','1400000US17135957700','1400000US17097864107','1400000US17031430400','1400000US17097864108','1400000US17073030201','1400000US17031410800','1400000US17073030202','1400000US17073030203','1400000US17179022100','1400000US17137951800','1400000US17199020500','1400000US17049950800','1400000US17167003901') OR GEO_ID IN ('1400000US17167003902','1400000US17031837800','1400000US17031550200','1400000US17031530600','1400000US17197883700','1400000US17017960100','1400000US17203030100','1400000US17007010100','1400000US17021958400','1400000US17031711000','1400000US17143005000','1400000US17031804901','1400000US17031824503','1400000US17031804902','1400000US17031824505','1400000US17031824506','1400000US17031824507','1400000US17201003100','1400000US17031650400','1400000US17089851400','1400000US17121952700','1400000US17161023600','1400000US17195000400','1400000US17031630800','1400000US17113002101','1400000US17095000800','1400000US17113002102','1400000US17131040300','1400000US17031060300','1400000US17031040700','1400000US17031381800','1400000US17031811200','1400000US17031221100','1400000US17031770201','1400000US17031750600','1400000US17031770202','1400000US17067953800','1400000US17001010200','1400000US17031180100','1400000US17167002600','1400000US17019001100','1400000US17025971900','1400000US17031160501','1400000US17029000300','1400000US17031160502','1400000US17115001900','1400000US17031836500','1400000US17031816900','1400000US17197882400','1400000US17031301701','1400000US17031301702','1400000US17031260700','1400000US17119402801','1400000US17119402802','1400000US17119402803','1400000US17031823200','1400000US17031803603','1400000US17031803604','1400000US17031803605','1400000US17031803606','1400000US17161022300','1400000US17031803607','1400000US17089850101','1400000US17031803608','1400000US17183000500','1400000US17089850103','1400000US17099962800','1400000US17089850105','1400000US17089850106','1400000US17031380500','1400000US17163504001','1400000US17163504002','1400000US17031803610','1400000US17031803611','1400000US17031828900','1400000US17031803612','1400000US17091012300','1400000US17031200200','1400000US17057953300','1400000US17043841801','1400000US17043841802','1400000US17167001300','1400000US17177000500','1400000US17115000600','1400000US17031835200','1400000US17031815600','1400000US17031661100','1400000US17117956500','1400000US17031071000','1400000US17197881105','1400000US17097861901','1400000US17031051400','1400000US17097861902','1400000US17197881107','1400000US17059972700','1400000US17197881108','1400000US17019005500','1400000US17031031800','1400000US17197881109','1400000US17119401500','1400000US17191955100','1400000US17031802300','1400000US17161021000','1400000US17031420200','1400000US17197881111','1400000US17197881112','1400000US17197881113','1400000US17197881115','1400000US17197881116','1400000US17111870702','1400000US17111870703','1400000US17111870704','1400000US17031827600','1400000US17091011000','1400000US17031520400','1400000US17089854501','1400000US17113005201','1400000US17031841900','1400000US17089854503','1400000US17113005202','1400000US17005951300','1400000US17055041000','1400000US17089854504','1400000US17031063400','1400000US17031271400','1400000US17143002800','1400000US17031251800','1400000US17103000700','1400000US17031814300','1400000US17183011200','1400000US17097860600','1400000US17031050100','1400000US17169970200','1400000US17031030500','1400000US17119400200','1400000US17031801000','1400000US17031839600','1400000US17031740400','1400000US17031150300','1400000US17031491400','1400000US17077011600','1400000US17031826301','1400000US17031806700','1400000US17031826303','1400000US17031826304','1400000US17089853200','1400000US17153971100','1400000US17031062100','1400000US17143001500','1400000US17031250500','1400000US17031230900','1400000US17019010900','1400000US17031813000','1400000US17081050100','1400000US17083010300','1400000US17165955800','1400000US17163501800','1400000US17043844901','1400000US17043844902','1400000US17137952300','1400000US17199021000','1400000US17157950700','1400000US17037001900','1400000US17031838300','1400000US17031818700','1400000US17139977000','1400000US17077010300','1400000US17031242900','1400000US17031825000','1400000US17031805401','1400000US17031805402','1400000US17161024101','1400000US17161024102','1400000US17095001300','1400000US17161024103','1400000US17031611700','1400000US17143000200','1400000US17173959600','1400000US17067954300','1400000US17163500500','1400000US17043843601','1400000US17043843602','1400000US17167003100','1400000US17031161000','1400000US17031690500','1400000US17031670900','1400000US17115002401','1400000US17115002402','1400000US17037000600','1400000US17031837000','1400000US17031817400','1400000US17031510200','1400000US17031831700','1400000US17097863701','1400000US17097863702','1400000US17031241600','1400000US17119403300','1400000US17179021701','1400000US17179021702','1400000US17031804102','1400000US17061974000','1400000US17031804104','1400000US17031804105','1400000US17031804106','1400000US17031804108','1400000US17031804109','1400000US17031610400','1400000US17099963300','1400000US17031020301','1400000US17031020302','1400000US17105960700','1400000US17031829401','1400000US17031809800','1400000US17031829402','1400000US17043842300','1400000US17065973200','1400000US17031730201','1400000US17031710600','1400000US17031730202','1400000US17031843700','1400000US17177001000','1400000US17031140100','1400000US17143004600','1400000US17115001100','1400000US17023060100','1400000US17201002700','1400000US17113001700','1400000US17031816100','1400000US17011965100','1400000US17117957000','1400000US17031830400','1400000US17031810800','1400000US17097862401','1400000US17097862402','1400000US17019006000','1400000US17125956800','1400000US17147954600','1400000US17031240300','1400000US17119402000','1400000US17031220701','1400000US17031220702','1400000US17179020400','1400000US17019000700','1400000US17099962000','1400000US17111871201','1400000US17111871202','1400000US17031340500','1400000US17111871205','1400000US17111871206','1400000US17111871207','1400000US17145030300','1400000US17111871208','1400000US17111871209','1400000US17031828100','1400000US17031808500','1400000US17031842400','1400000US17043841002','1400000US17043841003','1400000US17043841004','1400000US17031822801','1400000US17031822802','1400000US17143003300','1400000US17031460301','1400000US17031440700','1400000US17031460302','1400000US17161021900','1400000US17201001400','1400000US17113000400','1400000US17141961000','1400000US17043846701','1400000US17043846702','1400000US17031031000','1400000US17091011900','1400000US17097861105','1400000US17031580100','1400000US17097861106','1400000US17097861107','1400000US17097861108','1400000US17057952900','1400000US17167000900','1400000US17031834800','1400000US17031660700','1400000US17197880701','1400000US17197880702','1400000US17031090200','1400000US17031070600','1400000US17031807200','1400000US17031841100','1400000US17031821500','1400000US17075950200','1400000US17143002000','1400000US17031801901','1400000US17171970600','1400000US17031251000','1400000US17031801902','1400000US17161020600','1400000US17063000800','1400000US17201000101','1400000US17201000103','1400000US17201000104','1400000US17201000105','1400000US17001000900','1400000US17031190401','1400000US17129010200','1400000US17031170800','1400000US17031190402','1400000US17163502300','1400000US17043845401','1400000US17043845402','1400000US17031010100','1400000US17091010601','1400000US17157951200','1400000US17033880100','1400000US17091010602','1400000US17055040600','1400000US17031819200','1400000US17031700401','1400000US17031700402','1400000US17031813900','1400000US17097865501','1400000US17097865502','1400000US17123961100','1400000US17031110300','1400000US17031243400','1400000US17183010800','1400000US17031820201','1400000US17031800600','1400000US17031820202','1400000US17031230100','1400000US17031210501','1400000US17031210502','1400000US17019010100','1400000US17043844100','1400000US17031825900','1400000US17031691000','1400000US17031671400','1400000US17031310700','1400000US17195001800','1400000US17089852803','1400000US17031081300','1400000US17089852805','1400000US17089852806','1400000US17089852807','1400000US17089852808','1400000US17109010900','1400000US17031832200','1400000US17031812600','1400000US17097864203','1400000US17027900200','1400000US17097864204','1400000US17031242100','1400000US17097864205','1400000US17097864206','1400000US17135957800','1400000US17031222500','1400000US17031430500','1400000US17073030300','1400000US17031410900','1400000US17179022200','1400000US17137951900','1400000US17199020600','1400000US17017960200','1400000US17197883803','1400000US17197883804','1400000US17203030200','1400000US17007010200','1400000US17197883806','1400000US17197883808','1400000US17197883809','1400000US17021958500','1400000US17031711100','1400000US17031824601','1400000US17031824602','1400000US17031670100','1400000US17201003200','1400000US17031650500','1400000US17089851500','1400000US17161023700','1400000US17195000500','1400000US17197883810','1400000US17031630900','1400000US17197883811','1400000US17095000900','1400000US17131040400','1400000US17031060400','1400000US17031040800','1400000US17031381900','1400000US17031811301','1400000US17031811302','1400000US17031221200','1400000US17031770300','1400000US17107953000','1400000US17067953900','1400000US17001010300','1400000US17167002700','1400000US17019001201','1400000US17031160601','1400000US17029000400','1400000US17031160602','1400000US17019001203','1400000US17019001204','1400000US17019001205','1400000US17019001206','1400000US17031836600','1400000US17197882500','1400000US17031301801','1400000US17031301802','1400000US17031301803','1400000US17031280400','1400000US17031260800','1400000US17119402900','1400000US17031809000','1400000US17031823302','1400000US17031803701','1400000US17031823303','1400000US17031803702','1400000US17031823304','1400000US17061973600','1400000US17031100100','1400000US17089850201','1400000US17089850202','1400000US17183000600','1400000US17099962900','1400000US17031810000','1400000US17091012400','1400000US17031561000','1400000US17031200300','1400000US17057953400','1400000US17043841901','1400000US17043841902','1400000US17167001400','1400000US17031292400','1400000US17177000600','1400000US17031815701','1400000US17031815702','1400000US17031320100','1400000US17011964700','1400000US17031300500','1400000US17197881200','1400000US17117956600','1400000US17031071100','1400000US17059972800','1400000US17019005600','1400000US17031031900','1400000US17191955200','1400000US17031822000','1400000US17031802402','1400000US17031802403','1400000US17031802404','1400000US17161021100','1400000US17031420300','1400000US17111870803','1400000US17111870807','1400000US17111870808','1400000US17111870809','1400000US17031827700','1400000US17091011100','1400000US17031540101','1400000US17031520500','1400000US17031540102','1400000US17089854600','1400000US17043840600','1400000US17167000100','1400000US17005951400','1400000US17055041100','1400000US17031271500','1400000US17111870810','1400000US17143002900','1400000US17111870811','1400000US17031251900','1400000US17111870812','1400000US17103000800','1400000US17031834000','1400000US17097866000','1400000US17031814400','1400000US17133600101','1400000US17133600102','1400000US17031640300','1400000US17031050200','1400000US17169970300','1400000US17031030601','1400000US17031030603','1400000US17031030604','1400000US17031801100','1400000US17031839700','1400000US17197980100','1400000US17001000100','1400000US17031150401','1400000US17077011700','1400000US17031150402','1400000US17031826401','1400000US17031826402','1400000US17031806801','1400000US17031806802','1400000US17089853300','1400000US17031840700','1400000US17031062200','1400000US17143001600','1400000US17031250600','1400000US17031813100') OR GEO_ID IN ('1400000US17081050200','1400000US17165955900','1400000US17083010401','1400000US17163501900','1400000US17083010402','1400000US17199021100','1400000US17157950800','1400000US17031818800','1400000US17087980000','1400000US17139977100','1400000US17077010400','1400000US17021959000','1400000US17031805501','1400000US17031805502','1400000US17161024200','1400000US17195001000','1400000US17089852001','1400000US17089852002','1400000US17089852003','1400000US17095001400','1400000US17031611800','1400000US17143000300','1400000US17109010100','1400000US17031410100','1400000US17043843700','1400000US17101881000','1400000US17049950100','1400000US17167003201','1400000US17031161100','1400000US17167003202','1400000US17167003203','1400000US17115002500','1400000US17037000700','1400000US17031837100','1400000US17031817500','1400000US17197883000','1400000US17031510300','1400000US17031831800','1400000US17097863801','1400000US17119403401','1400000US17119403402','1400000US17179021801','1400000US17179021802','1400000US17031804201','1400000US17031804202','1400000US17071973300','1400000US17121952000','1400000US17031630100','1400000US17095000100','1400000US17099963400','1400000US17031020400','1400000US17105960800','1400000US17031829500','1400000US17031809900','1400000US17031730300','1400000US17043842400','1400000US17065973300','1400000US17031710700','1400000US17031843800','1400000US17177001100','1400000US17031140200','1400000US17115001200','1400000US17023060200','1400000US17201002800','1400000US17113001800','1400000US17031816200','1400000US17011965200','1400000US17117957100','1400000US17031830500','1400000US17031810900','1400000US17097862501','1400000US17097862502','1400000US17147954700','1400000US17119402100','1400000US17179020500','1400000US17019000800','1400000US17099962100','1400000US17031360200','1400000US17111871301','1400000US17031340600','1400000US17111871304','1400000US17111871305','1400000US17111871306','1400000US17111871307','1400000US17145030400','1400000US17031828201','1400000US17031808600','1400000US17031828202','1400000US17031842500','1400000US17043841102','1400000US17043841103','1400000US17031822900','1400000US17043841104','1400000US17111871310','1400000US17111871311','1400000US17143003401','1400000US17043841108','1400000US17143003402','1400000US17031460400','1400000US17043841109','1400000US17031440800','1400000US17201001500','1400000US17113000501','1400000US17113000502','1400000US17113000504','1400000US17113000505','1400000US17043841110','1400000US17043841111','1400000US17141961100','1400000US17043841112','1400000US17043841113','1400000US17043841114','1400000US17097861201','1400000US17097861202','1400000US17031031100','1400000US17031580200','1400000US17031834900','1400000US17031660800','1400000US17031090300','1400000US17031070700','1400000US17031807300','1400000US17031500100','1400000US17031841200','1400000US17031821600','1400000US17075950300','1400000US17143002100','1400000US17171970700','1400000US17031251100','1400000US17031231500','1400000US17161020700','1400000US17201000200','1400000US17063000900','1400000US17129010300','1400000US17031170900','1400000US17163502401','1400000US17043845502','1400000US17163502404','1400000US17043845505','1400000US17043845506','1400000US17091010701','1400000US17157951300','1400000US17031010201','1400000US17033880200','1400000US17043845507','1400000US17091010702','1400000US17031010202','1400000US17043845508','1400000US17043845509','1400000US17055040700','1400000US17031819300','1400000US17031720100','1400000US17043845510','1400000US17031700501','1400000US17097865600','1400000US17031700502','1400000US17123961200','1400000US17031110400','1400000US17031243500','1400000US17183010900','1400000US17031806001','1400000US17031806002','1400000US17031806003','1400000US17031806004','1400000US17031820300','1400000US17031800700','1400000US17031230200','1400000US17031210601','1400000US17031210602','1400000US17019010204','1400000US17165955100','1400000US17163501100','1400000US17043844201','1400000US17043844202','1400000US17031691100','1400000US17115003000','1400000US17031671500','1400000US17031310800','1400000US17089852903','1400000US17089852904','1400000US17031081401','1400000US17089852905','1400000US17031061800','1400000US17031081402','1400000US17089852906','1400000US17031081403','1400000US17089852907','1400000US17031818000','1400000US17031832300','1400000US17031812700','1400000US17097864303','1400000US17027900300','1400000US17031242200','1400000US17097864305','1400000US17097864306','1400000US17135957900','1400000US17031222600','1400000US17047956900','1400000US17097864307','1400000US17031430600','1400000US17073030400','1400000US17097864308','1400000US17179022300','1400000US17039971400','1400000US17199020700','1400000US17031611000','1400000US17051950500','1400000US17017960300','1400000US17197883902','1400000US17197883903','1400000US17197883904','1400000US17203030300','1400000US17007010300','1400000US17021958600','1400000US17031711200','1400000US17031824701','1400000US17031824702','1400000US17031670200','1400000US17201003300','1400000US17089851600','1400000US17195000600','1400000US17031080100','1400000US17031060500','1400000US17031040900','1400000US17031831000','1400000US17031811401','1400000US17031811402','1400000US17097863003','1400000US17097863004','1400000US17031221300','1400000US17031770400','1400000US17107953100','1400000US17179021000','1400000US17001010400','1400000US17167002801','1400000US17031160700','1400000US17167002802','1400000US17019001301','1400000US17019001302','1400000US17029000500','1400000US17031836700','1400000US17093890101','1400000US17093890102','1400000US17197882601','1400000US17197882602','1400000US17031260900','1400000US17031809100','1400000US17031843000','1400000US17031823400','1400000US17031803800','1400000US17061973700','1400000US17031100200','1400000US17085020100','1400000US17187870100','1400000US17121951600','1400000US17201002000','1400000US17089850301','1400000US17089850302','1400000US17183000700','1400000US17031380700','1400000US17031810100','1400000US17091012500','1400000US17031561100','1400000US17189950100','1400000US17057953500','1400000US17031200401','1400000US17031200402','1400000US17167001500','1400000US17031292500','1400000US17177000700','1400000US17031815800','1400000US17011964800','1400000US17031300600','1400000US17197881301','1400000US17197881302','1400000US17117956700','1400000US17031071200','1400000US17019005701','1400000US17019005702','1400000US17119401701','1400000US17191955300','1400000US17031822101','1400000US17031822102','1400000US17031802503','1400000US17031802504','1400000US17031802505','1400000US17031802506','1400000US17161021200','1400000US17031420400','1400000US17031400800','1400000US17099961701','1400000US17031191000','1400000US17099961702','1400000US17111870902','1400000US17111870903','1400000US17111870904','1400000US17111870905','1400000US17043846002','1400000US17043846003','1400000US17043846004','1400000US17031827801','1400000US17091011200','1400000US17031827802','1400000US17031827804','1400000US17031827805','1400000US17031520600','1400000US17089854700','1400000US17113005400','1400000US17005951500','1400000US17043840703','1400000US17055041200','1400000US17167000201','1400000US17031291200','1400000US17043840704','1400000US17167000202','1400000US17043840705','1400000US17043840706','1400000US17119401721','1400000US17119401722','1400000US17103000900','1400000US17097866100','1400000US17031814500','1400000US17031640400','1400000US17141960700','1400000US17149952400','1400000US17031050300','1400000US17031030701','1400000US17097860805','1400000US17031030702','1400000US17097860806','1400000US17031030703','1400000US17097860807','1400000US17097860808','1400000US17097860809','1400000US17031030706','1400000US17031801200','1400000US17031839800','1400000US17063000102','1400000US17063000103','1400000US17097860810','1400000US17001000201','1400000US17097860811','1400000US17001000202','1400000US17031170100','1400000US17031150501','1400000US17031150502','1400000US17031826500','1400000US17031806900','1400000US17031672000','1400000US17089853400','1400000US17031840800','1400000US17031062300','1400000US17031250700','1400000US17031813200','1400000US17183010100','1400000US17081050300','1400000US17083010500','1400000US17199021200','1400000US17031390100','1400000US17157950900','1400000US17051951000','1400000US17031818900','1400000US17139977200','1400000US17031490300','1400000US17031825200','1400000US17031805600','1400000US17161024300','1400000US17195001100','1400000US17089852101','1400000US17089852102','1400000US17095001500','1400000US17031611900','1400000US17031061000','1400000US17031590500','1400000US17109010200','1400000US17031410200','1400000US17043843800','1400000US17101881100','1400000US17167003300','1400000US17049950200','1400000US17031161200','1400000US17029001000','1400000US17115002601','1400000US17115002602','1400000US17037000800','1400000US17031817600','1400000US17197883100','1400000US17031831900','1400000US17015960100','1400000US17097863902','1400000US17097863903','1400000US17097863904','1400000US17119403502','1400000US17179021900','1400000US17071973400','1400000US17031804305','1400000US17031804306','1400000US17121952100','1400000US17161023000','1400000US17031630200','1400000US17031804308','1400000US17183001200','1400000US17031804309','1400000US17095000200','1400000US17099963500','1400000US17031040100','1400000US17031381200','1400000US17031020500','1400000US17105960900','1400000US17031804310','1400000US17031804311','1400000US17031829600','1400000US17031730400','1400000US17043842500','1400000US17031710800','1400000US17031843900','1400000US17167002000','1400000US17177001200','1400000US17031140301','1400000US17143004801','1400000US17031140302','1400000US17143004802','1400000US17115001300','1400000US17023060300','1400000US17201002900','1400000US17031816300','1400000US17011965300','1400000US17031301100','1400000US17117957200','1400000US17031830600','1400000US17031260100','1400000US17097862603','1400000US17097862604','1400000US17147954800','1400000US17031240500','1400000US17097862605','1400000US17119402200','1400000US17119403531','1400000US17119403532','1400000US17119403533','1400000US17031220901','1400000US17119403534','1400000US17031220902','1400000US17179020600','1400000US17019000901','1400000US17019000902','1400000US17031803005','1400000US17031803007','1400000US17031803008','1400000US17099962200','1400000US17111871402','1400000US17111871404','1400000US17045070100','1400000US17145030500','1400000US17031803010','1400000US17031828300','1400000US17031803012','1400000US17031803013','1400000US17031803014','1400000US17031803015','1400000US17031808702','1400000US17031803016','1400000US17031803017','1400000US17031842600','1400000US17043841204','1400000US17043841205','1400000US17043841206','1400000US17031480100','1400000US17043841207','1400000US17043841208','1400000US17031460500','1400000US17043841209','1400000US17031440900','1400000US17201001600','1400000US17031815000','1400000US17043841210','1400000US17141961200','1400000US17163503800','1400000US17097861301','1400000US17097861303','1400000US17031031200','1400000US17097861304','1400000US17031580300','1400000US17031560700','1400000US17031151001','1400000US17111870101','1400000US17031151002','1400000US17111870102','1400000US17031680500','1400000US17031660900','1400000US17197880901','1400000US17197880903','1400000US17197880905','1400000US17031827000','1400000US17031807400','1400000US17191954900','1400000US17031500200','1400000US17031841300','1400000US17031821700','1400000US17075950400','1400000US17143002200') OR GEO_ID IN ('1400000US17031251200','1400000US17103000100','1400000US17161020800','1400000US17201000300','1400000US17031190601','1400000US17031190602','1400000US17031600400','1400000US17163502500','1400000US17043845601','1400000US17043845602','1400000US17091010800','1400000US17031010300','1400000US17031351400','1400000US17033880300','1400000US17055040800','1400000US17031839000','1400000US17031819400','1400000US17031720200','1400000US17097865700','1400000US17077011000','1400000US17031130100','1400000US17123961300','1400000US17031110501','1400000US17031110502','1400000US17031806102','1400000US17031806103','1400000US17031806104','1400000US17031840000','1400000US17031820400','1400000US17031800800','1400000US17031230300','1400000US17031210700','1400000US17019010300','1400000US17163501200','1400000US17043844301','1400000US17043844304','1400000US17043844305','1400000US17043844306','1400000US17031350100','1400000US17043844307','1400000US17031691200','1400000US17115003100','1400000US17031671600','1400000US17031310900','1400000US17037001300','1400000US17031081500','1400000US17031061901','1400000US17031061902','1400000US17031818100','1400000US17031832400','1400000US17031812801','1400000US17097864402','1400000US17031812802','1400000US17097864403','1400000US17027900401','1400000US17031242300','1400000US17119404000','1400000US17027900402','1400000US17031450300','1400000US17031222700','1400000US17097864407','1400000US17031430700','1400000US17073030500','1400000US17097864408','1400000US17097864409','1400000US17179022400','1400000US17039971500','1400000US17199020800','1400000US17031611100','1400000US17099964000','1400000US17097864410','1400000US17097864411','1400000US17097864412','1400000US17051950600','1400000US17031570100','1400000US17017960400','1400000US17203030400','1400000US17007010400','1400000US17031281900','1400000US17043843000','1400000US17021958700','1400000US17031711300','1400000US17031824800','1400000US17031670300','1400000US17201003400','1400000US17195000700','1400000US17031080201','1400000US17031080202','1400000US17031831100','1400000US17053962000','1400000US17097863100','1400000US17031811500','1400000US17031241000','1400000US17031221400','1400000US17031770500','1400000US17107953200','1400000US17179021101','1400000US17001010500','1400000US17179021102','1400000US17101880700','1400000US17167002900','1400000US17019001400','1400000US17031160800','1400000US17029000600','1400000US17031836800','1400000US17093890201','1400000US17093890202','1400000US17105960100','1400000US17197882701','1400000US17197882702','1400000US17031809200','1400000US17031843100','1400000US17031823500','1400000US17143004000','1400000US17031803901','1400000US17031803902','1400000US17061973800','1400000US17031461000','1400000US17031100300','1400000US17085020200','1400000US17187870200','1400000US17089850400','1400000US17121951700','1400000US17161022600','1400000US17201002100','1400000US17183000800','1400000US17113001103','1400000US17113001104','1400000US17113001105','1400000US17113001106','1400000US17031810200','1400000US17163504302','1400000US17163504303','1400000US17091012600','1400000US17189950200','1400000US17057953600','1400000US17167001600','1400000US17177000800','1400000US17115000900','1400000US17031835500','1400000US17031815900','1400000US17031681000','1400000US17011964900','1400000US17031300700','1400000US17197881401','1400000US17197881402','1400000US17117956800','1400000US17031071300','1400000US17019005800','1400000US17119401800','1400000US17031822200','1400000US17031802605','1400000US17031440101','1400000US17161021300','1400000US17031420500','1400000US17031440102','1400000US17031802607','1400000US17031802608','1400000US17031802609','1400000US17099961800','1400000US17031191100','1400000US17043846102','1400000US17031802610','1400000US17043846103','1400000US17043846104','1400000US17031827901','1400000US17043846105','1400000US17091011300','1400000US17031827902','1400000US17043846106','1400000US17089854800','1400000US17043840801','1400000US17113005501','1400000US17043840802','1400000US17113005502','1400000US17167000300','1400000US17031834200','1400000US17097866200','1400000US17031814600','1400000US17031640500','1400000US17141960800','1400000US17149952500','1400000US17197880105','1400000US17197880106','1400000US17197880107','1400000US17097860903','1400000US17031030800','1400000US17097860904','1400000US17197880109','1400000US17069970900','1400000US17097860905','1400000US17009970400','1400000US17097860906','1400000US17163504351','1400000US17163504352','1400000US17163504353','1400000US17163504354','1400000US17031801300','1400000US17163504355','1400000US17031839900','1400000US17063000200','1400000US17197880111','1400000US17197880112','1400000US17197880113','1400000US17197880114','1400000US17197880115','1400000US17197880116','1400000US17031170200','1400000US17197880117','1400000US17197880118','1400000US17031150600','1400000US17197880119','1400000US17031826600','1400000US17197880120','1400000US17197880121','1400000US17089853500','1400000US17031062400','1400000US17143001800','1400000US17031250800','1400000US17031813301','1400000US17031813302','1400000US17031431200','1400000US17073031000','1400000US17183010200','1400000US17081050400','1400000US17199021300','1400000US17031390200','1400000US17031838600','1400000US17051951100','1400000US17031490400','1400000US17077010600','1400000US17031825302','1400000US17031805701','1400000US17031825303','1400000US17031805702','1400000US17031825304','1400000US17161024400','1400000US17195001200','1400000US17089852201','1400000US17089852202','1400000US17095001600','1400000US17031061100','1400000US17143000500','1400000US17031590600','1400000US17109010300','1400000US17031812000','1400000US17043843900','1400000US17167003400','1400000US17049950300','1400000US17031161300','1400000US17029001100','1400000US17115002700','1400000US17037000900','1400000US17031837300','1400000US17031817700','1400000US17031530100','1400000US17015960200','1400000US17197883206','1400000US17197883208','1400000US17197883209','1400000US17119403601','1400000US17119403603','1400000US17119403604','1400000US17031824003','1400000US17031824004','1400000US17031804403','1400000US17031824005','1400000US17031804404','1400000US17031824006','1400000US17071973500','1400000US17031804405','1400000US17031804406','1400000US17121952200','1400000US17161023100','1400000US17197883210','1400000US17031630300','1400000US17183001300','1400000US17197883211','1400000US17095000300','1400000US17197883212','1400000US17099963600','1400000US17197883213','1400000US17197883214','1400000US17197883215','1400000US17197883216','1400000US17031040201','1400000US17031040202','1400000US17031020601','1400000US17031020602','1400000US17185957200','1400000US17031829700','1400000US17031750100','1400000US17031730500','1400000US17043842601','1400000US17031710900','1400000US17043842602','1400000US17167002100','1400000US17043842603','1400000US17043842604','1400000US17177001300','1400000US17043842605','1400000US17031140400','1400000US17143004901','1400000US17143004902','1400000US17115001400','1400000US17023060400','1400000US17031836000','1400000US17031816401','1400000US17031816402','1400000US17011965400','1400000US17031301200','1400000US17031830700','1400000US17053961600','1400000US17097862700','1400000US17031260200','1400000US17031240600','1400000US17119402300','1400000US17179020700','1400000US17031803100','1400000US17099962300','1400000US17111871500','1400000US17045070200','1400000US17145030600','1400000US17031828401','1400000US17031808800','1400000US17031828402','1400000US17113006000','1400000US17175951400','1400000US17031480200','1400000US17043841307','1400000US17143003601','1400000US17043841308','1400000US17143003602','1400000US17031460600','1400000US17201001700','1400000US17031815100','1400000US17043841310','1400000US17117956000','1400000US17141961300','1400000US17043841312','1400000US17043841313','1400000US17043841314','1400000US17043841315','1400000US17097861402','1400000US17043841316','1400000US17097861403','1400000US17163503903','1400000US17031031300','1400000US17097861404','1400000US17163503904','1400000US17043841318','1400000US17119401000','1400000US17163503905','1400000US17031580400','1400000US17163503906','1400000US17031560800','1400000US17181950100','1400000US17043841320','1400000US17043841321','1400000US17043841322','1400000US17043841323','1400000US17043841324','1400000US17043841325','1400000US17043841326','1400000US17031151100','1400000US17043841327','1400000US17111870200','1400000US17031680600','1400000US17031827100','1400000US17031807500','1400000US17043840000','1400000US17089854001','1400000US17031500300','1400000US17089854002','1400000US17031841400','1400000US17031821800','1400000US17075950500','1400000US17143002300','1400000US17031251300','1400000US17103000200','1400000US17161020900','1400000US17201000401','1400000US17201000402','1400000US17201000403','1400000US17031190701','1400000US17031190702','1400000US17031620100','1400000US17043845701','1400000US17097860101','1400000US17043845702','1400000US17163502602','1400000US17043845703','1400000US17097860103','1400000US17163502603','1400000US17043845704','1400000US17097860104','1400000US17091010900','1400000US17031010400','1400000US17031351500','1400000US17033880400','1400000US17055040900','1400000US17031290900','1400000US17031839100','1400000US17031819500','1400000US17031720300','1400000US17097865801','1400000US17077011100','1400000US17097865802','1400000US17031130200','1400000US17123961400','1400000US17031806201','1400000US17031806202','1400000US17031840100','1400000US17151971200','1400000US17031820501','1400000US17031800900','1400000US17031820502','1400000US17031230400','1400000US17031210800','1400000US17019010400','1400000US17163501300','1400000US17043844401','1400000US17043844402','1400000US17035972400','1400000US17031691300','1400000US17037001400','1400000US17031081600','1400000US17031818200','1400000US17031832500','1400000US17031812900','1400000US17027900500','1400000US17031242400','1400000US17097864505','1400000US17119404100','1400000US17031222800','1400000US17031430800','1400000US17073030600','1400000US17039971600','1400000US17199020900','1400000US17031611200','1400000US17099964100','1400000US17097864510','1400000US17097864511','1400000US17097864512','1400000US17051950700','1400000US17097864513','1400000US17097864514','1400000US17097864515','1400000US17031570200','1400000US17097864516','1400000US17097864517','1400000US17097864518','1400000US17097864519','1400000US17017960500','1400000US17139976900','1400000US17007010500','1400000US17203030501','1400000US17203030502','1400000US17173959100','1400000US17043843100','1400000US17021958800','1400000US17031711400','1400000US17097864520','1400000US17097864521','1400000US17031824900','1400000US17097864522','1400000US17031670400','1400000US17201003500','1400000US17037000100','1400000US17195000800','1400000US17089851801','1400000US17031080300','1400000US17031831200','1400000US17031811600','1400000US17097863201','1400000US17097863202','1400000US17031241100','1400000US17031221500','1400000US17107953300','1400000US17031770601','1400000US17031770602','1400000US17179021201','1400000US17001010600','1400000US17179021202','1400000US17179021203','1400000US17101880800','1400000US17031160900','1400000US17029000700','1400000US17031836900','1400000US17093890301','1400000US17093890302','1400000US17105960200','1400000US17197882801','1400000US17197882802','1400000US17031809300','1400000US17031710100','1400000US17031843200','1400000US17031823602','1400000US17031823603','1400000US17143004101') OR GEO_ID IN ('1400000US17031823604','1400000US17061973900','1400000US17143004102','1400000US17031823605','1400000US17031100400','1400000US17085020300','1400000US17187870300','1400000US17089850500','1400000US17121951800','1400000US17201002200','1400000US17113001200','1400000US17183000900','1400000US17031810301','1400000US17031810302','1400000US17125956300','1400000US17189950300','1400000US17057953700','1400000US17167001700','1400000US17019000200','1400000US17177000900','1400000US17031835600','1400000US17159978000','1400000US17031681100','1400000US17031320400','1400000US17031300800','1400000US17197881500','1400000US17117956900','1400000US17031071400','1400000US17019005900','1400000US17119401901','1400000US17031808001','1400000US17031808002','1400000US17119401903','1400000US17119401904','1400000US17031822301','1400000US17031822302','1400000US17031802701','1400000US17031802702','1400000US17031440201','1400000US17161021400','1400000US17031420600','1400000US17031440202','1400000US17099961900','1400000US17031191200','1400000US17163503100','1400000US17043846201','1400000US17043846202','1400000US17043846203','1400000US17043846205','1400000US17091011400','1400000US17043846206','1400000US17003957600','1400000US17043846207','1400000US17043846208','1400000US17043846209','1400000US17089854900','1400000US17043840901','1400000US17113005601','1400000US17113005602','1400000US17167000400','1400000US17043840904','1400000US17031271800','1400000US17043840906','1400000US17043840907','1400000US17043840908','1400000US17031834300','1400000US17031814700','1400000US17133600401','1400000US17133600402','1400000US17031640600','1400000US17043840910','1400000US17197880202','1400000US17043840911','1400000US17141960900','1400000US17197880203','1400000US17197880204','1400000US17149952600','1400000US17031070101','1400000US17031050500','1400000US17031070102','1400000US17031070103','1400000US17031030900','1400000US17119400600','1400000US17009970500','1400000US17031821001','1400000US17031801400','1400000US17031821002','1400000US17161020100','1400000US17063000300','1400000US17001000400','1400000US17031170300','1400000US17031150700','1400000US17031283800','1400000US17031826700','1400000US17091010100','1400000US17089853600','1400000US17055040100','1400000US17031062500','1400000US17031270500','1400000US17143001900','1400000US17031833000','1400000US17097865000','1400000US17031813400','1400000US17073031100','1400000US17031431301','1400000US17183010300','1400000US17031431302','1400000US17081050500','1400000US17199021400','1400000US17031390300','1400000US17031800100','1400000US17041952000','1400000US17031838700','1400000US17031490500','1400000US17077010700','1400000US17193958000','1400000US17031825400','1400000US17031805801','1400000US17031805802','1400000US17031310200','1400000US17089852300','1400000US17161024500','1400000US17195001300','1400000US17201004001','1400000US17201004002','1400000US17201004003','1400000US17031061200','1400000US17143000600','1400000US17031590700','1400000US17109010400','1400000US17031812100','1400000US17135957300','1400000US17163500900','1400000US17137951400','1400000US17167003500','1400000US17199020100','1400000US17049950400','1400000US17029001200','1400000US17031690900','1400000US17115002800','1400000US17031837400','1400000US17031530200','1400000US17197883303','1400000US17197883304','1400000US17015960300','1400000US17197883305','1400000US17197883306','1400000US17197883307','1400000US17119403701','1400000US17119403702','1400000US17031824105','1400000US17031824106','1400000US17031804505','1400000US17031824107','1400000US17031804506','1400000US17031824108','1400000US17089851000','1400000US17121952300','1400000US17161023200','1400000US17031804507','1400000US17031630400','1400000US17031804508','1400000US17031804509','1400000US17095000400','1400000US17031610800','1400000US17099963700','1400000US17031040300','1400000US17031381400','1400000US17031020701','1400000US17031020702','1400000US17031804510','1400000US17185957300','1400000US17031804511','1400000US17031824113','1400000US17031829800','1400000US17031824114','1400000US17031824115','1400000US17031824116','1400000US17031824117','1400000US17031824119','1400000US17031750200','1400000US17031730600','1400000US17043842702','1400000US17167002200','1400000US17043842703','1400000US17031160100','1400000US17043842704','1400000US17031140500','1400000US17043842706','1400000US17043842708','1400000US17043842709','1400000US17115001500','1400000US17031824120','1400000US17031824121','1400000US17031836100','1400000US17031824122','1400000US17031816500','1400000US17031824123','1400000US17079977300','1400000US17011965500','1400000US17197882000','1400000US17043842710','1400000US17043842711','1400000US17031830800','1400000US17053961700','1400000US17097862800','1400000US17031260300','1400000US17031240700','1400000US17119402400','1400000US17107952900','1400000US17179020800','1400000US17031803200','1400000US17183000100','1400000US17099962400','1400000US17031380100','1400000US17111871600','1400000US17045070300','1400000US17031808900','1400000US17031828503','1400000US17031828504','1400000US17031828505','1400000US17031828506','1400000US17043841401','1400000US17175951500','1400000US17031842800','1400000US17043841403','1400000US17043841404','1400000US17177000100','1400000US17143003700','1400000US17031480300','1400000US17031460700','1400000US17115000200','1400000US17201001800','1400000US17031815200','1400000US17117956100','1400000US17141961400','1400000US17031051000','1400000US17031031400','1400000US17097861504','1400000US17097861505','1400000US17119401100','1400000US17097861506','1400000US17031580501','1400000US17097861507','1400000US17031560900','1400000US17031580502','1400000US17097861508','1400000US17097861509','1400000US17181950200','1400000US17097861510','1400000US17031151200','1400000US17111870301','1400000US17111870302','1400000US17031827200','1400000US17031807600','1400000US17089854100','1400000US17043840101','1400000US17031841500','1400000US17043840102','1400000US17043840103','1400000US17031821900','1400000US17043840104','1400000US17075950600','1400000US17031063000','1400000US17143002400','1400000US17031251400','1400000US17103000300','1400000US17201000501','1400000US17201000502','1400000US17201000504','1400000US17031190800','1400000US17201000506','1400000US17201000507','1400000US17031620200','1400000US17081051000','1400000US17031600600','1400000US17097860200','1400000US17163502700','1400000US17043845802','1400000US17043845803','1400000US17031030101','1400000US17043845805','1400000US17031030102','1400000US17031010501','1400000US17031030103','1400000US17033880500','1400000US17043845807','1400000US17031010502','1400000US17031030104','1400000US17043845808','1400000US17031010503','1400000US17043845809','1400000US17201000510','1400000US17201000511','1400000US17201000512','1400000US17201000513','1400000US17201000514','1400000US17031839200','1400000US17031819600','1400000US17031720400','1400000US17043845810','1400000US17043845811','1400000US17031833900','1400000US17031491000','1400000US17077011200','1400000US17031130300','1400000US17123961500','1400000US17031806300','1400000US17031840200','1400000US17151971300','1400000US17031820603','1400000US17031820604','1400000US17031820605','1400000US17031230500','1400000US17031820606','1400000US17031210900','1400000US17019010500','1400000US17163501400','1400000US17043844501','1400000US17043844502','1400000US17167004000','1400000US17035972500','1400000US17031691400','1400000US17031671800','1400000US17037001500','1400000US17031081700','1400000US17031818300','1400000US17031832600','1400000US17097864601','1400000US17097864602','1400000US17031470100','1400000US17027900601','1400000US17031242500','1400000US17027900602','1400000US17031222900','1400000US17031430900','1400000US17039971700','1400000US17031805001','1400000US17031805002','1400000US17031611300','1400000US17099964200','1400000US17051950800','1400000US17031570300','1400000US17203030601','1400000US17007010601','1400000US17203030602','1400000US17007010602','1400000US17173959200','1400000US17043843200','1400000US17021958900','1400000US17031711500','1400000US17025972000','1400000US17115002000','1400000US17031670500','1400000US17037000200','1400000US17195000900','1400000US17201003601','1400000US17201003602','1400000US17201003604','1400000US17031080400','1400000US17089851904','1400000US17201003605','1400000US17089851905','1400000US17201003606','1400000US17031060800','1400000US17089851907','1400000US17089851908','1400000US17089851909','1400000US17031817000','1400000US17031831300','1400000US17087977600','1400000US17097863300','1400000US17031811701','1400000US17031811702','1400000US17031241200','1400000US17031221600','1400000US17031770700','1400000US17089851910','1400000US17107953400','1400000US17101880900','1400000US17029000800','1400000US17093890400','1400000US17105960300','1400000US17197882900','1400000US17031280800','1400000US17031829000','1400000US17031809400','1400000US17031710200','1400000US17031843300','1400000US17031823702','1400000US17143004200','1400000US17031823703','1400000US17031120100','1400000US17031823704','1400000US17031823705','1400000US17031100500','1400000US17187870400','1400000US17085020401','1400000US17089850600','1400000US17121951900','1400000US17161022800','1400000US17085020402','1400000US17201002301','1400000US17113001301','1400000US17201002302','1400000US17113001302','1400000US17113001303','1400000US17031830001','1400000US17097862000','1400000US17163504500','1400000US17031810400','1400000US17031830003','1400000US17031830004','1400000US17031830005','1400000US17125956400','1400000US17031830006','1400000US17031830007','1400000US17031220300','1400000US17031830008','1400000US17189950400','1400000US17057953800','1400000US17127970100','1400000US17167001800','1400000US17019000301','1400000US17019000302','1400000US17031835700','1400000US17159978100','1400000US17031681200','1400000US17031300900','1400000US17197881601','1400000US17197881603','1400000US17197881604','1400000US17031071500','1400000US17031808100','1400000US17031842000','1400000US17031822400','1400000US17031802801','1400000US17031802802','1400000US17013951200','1400000US17031440300','1400000US17161021500','1400000US17201001000','1400000US17031420700','1400000US17031191301','1400000US17031191302','1400000US17163503202','1400000US17163503203','1400000US17043846304','1400000US17043846305','1400000US17091011500','1400000US17003957700','1400000US17043846307','1400000US17031560100','1400000US17043846308','1400000US17113005700','1400000US17167000501','1400000US17167000503','1400000US17167000504','1400000US17043846310','1400000US17043846311','1400000US17163503211','1400000US17031834400','1400000US17043846312','1400000US17043846313','1400000US17031814800','1400000US17043846314','1400000US17043846315','1400000US17133600501','1400000US17031660301','1400000US17133600502','1400000US17031640700','1400000US17031660302','1400000US17197880303','1400000US17197880304','1400000US17031070200','1400000US17149952700','1400000US17197880305','1400000US17197880306','1400000US17031050600','1400000US17197880307','1400000US17197880308','1400000US17197880309','1400000US17119400700','1400000US17031821101','1400000US17031801500','1400000US17031821102','1400000US17161020200','1400000US17063000400','1400000US17197880310','1400000US17197880312','1400000US17197880313','1400000US17197880314','1400000US17001000500','1400000US17019011000','1400000US17031170400','1400000US17031150800','1400000US17043845000','1400000US17031826800','1400000US17091010201','1400000US17091010202') OR GEO_ID IN ('1400000US17037002000','1400000US17055040200','1400000US17031062600','1400000US17031833100','1400000US17031813500','1400000US17031243000','1400000US17031431400','1400000US17073031200','1400000US17183010400','1400000US17081050600','1400000US17031390400','1400000US17031800200','1400000US17041952100','1400000US17031838800','1400000US17031210100','1400000US17031490600','1400000US17077010800','1400000US17193958100','1400000US17031825501','1400000US17031805901','1400000US17031825503','1400000US17031805902','1400000US17031825504','1400000US17031825505','1400000US17031310300','1400000US17201004100','1400000US17195001400','1400000US17089852401','1400000US17089852402','1400000US17089852403','1400000US17109010500','1400000US17031812200','1400000US17135957400','1400000US17031430101','1400000US17031410500','1400000US17031430102','1400000US17137951500','1400000US17049950500','1400000US17167003601','1400000US17199020201','1400000US17167003602','1400000US17199020202','1400000US17167003603','1400000US17167003604','1400000US17115002901','1400000US17115002902','1400000US17115002903','1400000US17115002904','1400000US17031817900','1400000US17031530300','1400000US17197883401','1400000US17197883402','1400000US17015960400','1400000US17119403801','1400000US17119403802','1400000US17021958100','1400000US17031804603','1400000US17031650100','1400000US17031804606','1400000US17121952400','1400000US17161023300','1400000US17195000100','1400000US17031804607','1400000US17089851101','1400000US17031630500','1400000US17031804608','1400000US17089851102','1400000US17031804609','1400000US17095000500','1400000US17099963800','1400000US17031040401','1400000US17031381500','1400000US17031040402','1400000US17031020801','1400000US17031020802','1400000US17031804610','1400000US17185957400','1400000US17031804611','1400000US17031829901','1400000US17031829902','1400000US17155954500','1400000US17031750300','1400000US17031730700','1400000US17043842800','1400000US17167002300','1400000US17031160200','1400000US17031140601','1400000US17031140602','1400000US17115001600','1400000US17031836200','1400000US17031816600','1400000US17079977400','1400000US17011965600','1400000US17197882100','1400000US17031830900','1400000US17053961800','1400000US17097862901','1400000US17097862902','1400000US17031260400','1400000US17031240800','1400000US17119402500','1400000US17179020900','1400000US17031803300','1400000US17161022000','1400000US17031421200','1400000US17183000200','1400000US17099962500','1400000US17031380200','1400000US17045070400','1400000US17031828601','1400000US17091012000','1400000US17031828602','1400000US17057953000','1400000US17043841501')"</Process></lineage><itemProps><itemName Sync="TRUE">EUS0</itemName><imsContentType Sync="TRUE">002</imsContentType><itemSize Sync="TRUE">0.000</itemSize><itemLocation><linkage Sync="TRUE">file://\\DADSB219\E\arcgisserver\arcgisjobs\download_shape_gpserver\j4da1b4d9262c4dd7a12e8fe58b91a1fb\scratch\EUS0.shp</linkage><protocol Sync="TRUE">Local Area Network</protocol></itemLocation></itemProps><coordRef><type Sync="TRUE">Projected</type><geogcsn Sync="TRUE">GCS_WGS_1984</geogcsn><projcsn Sync="TRUE">WGS_1984_Web_Mercator_Auxiliary_Sphere</projcsn><peXml Sync="TRUE">&lt;ProjectedCoordinateSystem xsi:type='typens:ProjectedCoordinateSystem' xmlns:xsi='http://www.w3.org/2001/XMLSchema-instance' xmlns:xs='http://www.w3.org/2001/XMLSchema' xmlns:typens='http://www.esri.com/schemas/ArcGIS/10.0'&gt;&lt;WKT&gt;PROJCS[&amp;quot;WGS_1984_Web_Mercator_Auxiliary_Sphere&amp;quot;,GEOGCS[&amp;quot;GCS_WGS_1984&amp;quot;,DATUM[&amp;quot;D_WGS_1984&amp;quot;,SPHEROID[&amp;quot;WGS_1984&amp;quot;,6378137.0,298.257223563]],PRIMEM[&amp;quot;Greenwich&amp;quot;,0.0],UNIT[&amp;quot;Degree&amp;quot;,0.0174532925199433]],PROJECTION[&amp;quot;Mercator_Auxiliary_Sphere&amp;quot;],PARAMETER[&amp;quot;False_Easting&amp;quot;,0.0],PARAMETER[&amp;quot;False_Northing&amp;quot;,0.0],PARAMETER[&amp;quot;Central_Meridian&amp;quot;,0.0],PARAMETER[&amp;quot;Standard_Parallel_1&amp;quot;,0.0],PARAMETER[&amp;quot;Auxiliary_Sphere_Type&amp;quot;,0.0],UNIT[&amp;quot;Meter&amp;quot;,1.0],AUTHORITY[&amp;quot;EPSG&amp;quot;,3857]]&lt;/WKT&gt;&lt;XOrigin&gt;-20037700&lt;/XOrigin&gt;&lt;YOrigin&gt;-30241100&lt;/YOrigin&gt;&lt;XYScale&gt;148923141.92838538&lt;/XYScale&gt;&lt;ZOrigin&gt;-100000&lt;/ZOrigin&gt;&lt;ZScale&gt;10000&lt;/ZScale&gt;&lt;MOrigin&gt;-100000&lt;/MOrigin&gt;&lt;MScale&gt;10000&lt;/MScale&gt;&lt;XYTolerance&gt;0.001&lt;/XYTolerance&gt;&lt;ZTolerance&gt;0.001&lt;/ZTolerance&gt;&lt;MTolerance&gt;0.001&lt;/MTolerance&gt;&lt;HighPrecision&gt;true&lt;/HighPrecision&gt;&lt;WKID&gt;3857&lt;/WKID&gt;&lt;/ProjectedCoordinateSystem&gt;</peXml></coordRef></DataProperties><SyncDate>20150402</SyncDate><SyncTime>18014600</SyncTime><ModDate>20150402</ModDate><ModTime>18014600</ModTime></Esri><dataIdInfo><envirDesc Sync="TRUE">Microsoft Windows Server 2008 R2 Version 6.1 (Build 7601) Service Pack 1; ESRI ArcGIS 10.0.0.2414</envirDesc><dataLang><languageCode value="eng" country="USA"></languageCode></dataLang><idCitation><resTitle Sync="TRUE">EUS0</resTitle><presForm><PresFormCd value="005"></PresFormCd></presForm></idCitation><descKeys><thesaName uuidref="723f6998-058e-11dc-8314-0800200c9a66"></thesaName><keyword Sync="TRUE">002</keyword></descKeys><spatRpType><SpatRepTypCd value="001"></SpatRepTypCd></spatRpType></dataIdInfo><mdLang><languageCode value="eng"></languageCode></mdLang><distInfo><distFormat><formatName Sync="TRUE">Shapefile</formatName></distFormat><distTranOps><transSize Sync="TRUE">0.000</transSize></distTranOps></distInfo><mdHrLv><ScopeCd value="005"></ScopeCd></mdHrLv><mdHrLvName Sync="TRUE">dataset</mdHrLvName><refSysInfo><RefSystem><refSysID><identCode code="3857"></identCode><idCodeSpace Sync="TRUE">EPSG</idCodeSpace><idVersion Sync="TRUE">7.4.1</idVersion></refSysID></RefSystem></refSysInfo><spdoinfo><ptvctinf><esriterm Name="EUS0"><efeatyp Sync="TRUE">Simple</efeatyp><efeageom Sync="TRUE">4</efeageom><esritopo Sync="TRUE">FALSE</esritopo><efeacnt Sync="TRUE">0</efeacnt><spindex Sync="TRUE">FALSE</spindex><linrefer Sync="TRUE">FALSE</linrefer></esriterm></ptvctinf></spdoinfo><spatRepInfo><VectSpatRep><topLvl><TopoLevCd value="001"></TopoLevCd></topLvl><geometObjs><geoObjTyp><GeoObjTypCd value="002"></GeoObjTypCd><geoObjCnt Sync="TRUE">0</geoObjCnt></geoObjTyp></geometObjs></VectSpatRep></spatRepInfo><eainfo><detailed Name="EUS0"><enttyp><enttypl Sync="TRUE">EUS0</enttypl><enttypt Sync="TRUE">Feature Class</enttypt><enttypc Sync="TRUE">0</enttypc></enttyp><attr><attrlabl Sync="TRUE">FID</attrlabl><attalias Sync="TRUE">FID</attalias><attrtype Sync="TRUE">OID</attrtype><attwidth Sync="TRUE">4</attwidth><atprecis Sync="TRUE">0</atprecis><attscale Sync="TRUE">0</attscale><attrdef Sync="TRUE">Internal feature number.</attrdef><attrdefs Sync="TRUE">ESRI</attrdefs><attrdomv><udom Sync="TRUE">Sequential unique whole numbers that are automatically generated.</udom></attrdomv></attr><attr><attrlabl Sync="TRUE">Shape</attrlabl><attalias Sync="TRUE">Shape</attalias><attrtype Sync="TRUE">Geometry</attrtype><attwidth Sync="TRUE">0</attwidth><atprecis Sync="TRUE">0</atprecis><attscale Sync="TRUE">0</attscale><attrdef Sync="TRUE">Feature geometry.</attrdef><attrdefs Sync="TRUE">ESRI</attrdefs><attrdomv><udom Sync="TRUE">Coordinates defining the features.</udom></attrdomv></attr><attr><attrlabl Sync="TRUE">GEO_ID</attrlabl><attalias Sync="TRUE">GEO_ID</attalias><attrtype Sync="TRUE">String</attrtype><attwidth Sync="TRUE">60</attwidth><atprecis Sync="TRUE">0</atprecis><attscale Sync="TRUE">0</attscale></attr><attr><attrlabl Sync="TRUE">STATE</attrlabl><attalias Sync="TRUE">STATE</attalias><attrtype Sync="TRUE">String</attrtype><attwidth Sync="TRUE">2</attwidth><atprecis Sync="TRUE">0</atprecis><attscale Sync="TRUE">0</attscale></attr><attr><attrlabl Sync="TRUE">COUNTY</attrlabl><attalias Sync="TRUE">COUNTY</attalias><attrtype Sync="TRUE">String</attrtype><attwidth Sync="TRUE">3</attwidth><atprecis Sync="TRUE">0</atprecis><attscale Sync="TRUE">0</attscale></attr><attr><attrlabl Sync="TRUE">TRACT</attrlabl><attalias Sync="TRUE">TRACT</attalias><attrtype Sync="TRUE">String</attrtype><attwidth Sync="TRUE">6</attwidth><atprecis Sync="TRUE">0</atprecis><attscale Sync="TRUE">0</attscale></attr><attr><attrlabl Sync="TRUE">NAME</attrlabl><attalias Sync="TRUE">NAME</attalias><attrtype Sync="TRUE">String</attrtype><attwidth Sync="TRUE">90</attwidth><atprecis Sync="TRUE">0</atprecis><attscale Sync="TRUE">0</attscale></attr><attr><attrlabl Sync="TRUE">LSAD</attrlabl><attalias Sync="TRUE">LSAD</attalias><attrtype Sync="TRUE">String</attrtype><attwidth Sync="TRUE">7</attwidth><atprecis Sync="TRUE">0</atprecis><attscale Sync="TRUE">0</attscale></attr><attr><attrlabl Sync="TRUE">SHAPE_AREA</attrlabl><attalias Sync="TRUE">SHAPE_AREA</attalias><attrtype Sync="TRUE">Double</attrtype><attwidth Sync="TRUE">19</attwidth><atprecis Sync="TRUE">0</atprecis><attscale Sync="TRUE">0</attscale><attrdef Sync="TRUE">Area of feature in internal units squared.</attrdef><attrdefs Sync="TRUE">ESRI</attrdefs><attrdomv><udom Sync="TRUE">Positive real numbers that are automatically generated.</udom></attrdomv></attr><attr><attrlabl Sync="TRUE">SHAPE_LEN</attrlabl><attalias Sync="TRUE">SHAPE_LEN</attalias><attrtype Sync="TRUE">Double</attrtype><attwidth Sync="TRUE">19</attwidth><atprecis Sync="TRUE">0</atprecis><attscale Sync="TRUE">0</attscale></attr></detailed></eainfo><mdDateSt Sync="TRUE">20150402</mdDateSt></metadata>
